[
  { "#": 601, "Pousada": "Pousada Maraubrasil", "E-mail": "contato@maraubrasil.com.br", "Whatsapp": "557332586239", "Qtd Quartos": 20, "Local / Praia": "Taipu de Fora", "Cidade": "Maraú", "UF": "BA", "Valores Estimados": "R$ 1100 - R$ 2800", "Qualificacao": "Premium VIP Elite", "Validacao": "VALIDADO", "Comportamento de Compra": "Elite Prime VIP", "Sinais de Intencao": "Necessidade escala", "Redes Sociais": "instagram.com/pousadamaraubrasil", "Site": "maraubrasil.com.br", "Telefone": "7332586239", "Score Qual.": 100, "Score Valid.": 100 },
  { "#": 602, "Pousada": "Pousada Lagoa do Cassange", "E-mail": "reservas@cassange.com.br", "Whatsapp": "557332582155", "Qtd Quartos": 12, "Local / Praia": "Cassange", "Cidade": "Maraú", "UF": "BA", "Valores Estimados": "R$ 900 - R$ 2500", "Qualificacao": "Eco Luxury VIP Boutique", "Validacao": "VALIDADO", "Comportamento de Compra": "Elite Prime Luxo", "Sinais de Intencao": "Atendimento VIP", "Redes Sociais": "instagram.com/pousadalagoadocassange", "Site": "cassange.com.br", "Telefone": "7332582155", "Score Qual.": 100, "Score Valid.": 100 },
  { "#": 603, "Pousada": "Pousada Bromélias Maraú", "E-mail": "contato@bromeliasmarau.com.br", "Whatsapp": "557332581126", "Qtd Quartos": 10, "Local / Praia": "Barra Grande", "Cidade": "Maraú", "UF": "BA", "Valores Estimados": "R$ 600 - R$ 1500", "Qualificacao": "Design VIP Boutique", "Validacao": "VALIDADO", "Comportamento de Compra": "Casais Elite VIP", "Sinais de Intencao": "Marketing WA", "Redes Sociais": "instagram.com/pousadabromelias", "Site": "bromelias.com.br", "Telefone": "7332581126", "Score Qual.": 95, "Score Valid.": 100 },
  { "#": 604, "Pousada": "Pousada Barra Velha Maraú", "E-mail": "reservas@barravelhamarau.com.br", "Whatsapp": "557332581127", "Qtd Quartos": 15, "Local / Praia": "Barra Grande", "Cidade": "Maraú", "UF": "BA", "Valores Estimados": "R$ 550 - R$ 1300", "Qualificacao": "Tradicional VIP Elite", "Validacao": "VALIDADO", "Comportamento de Compra": "Turista Prime VIP", "Sinais de Intencao": "Necessidade escala", "Redes Sociais": "instagram.com/pousadabarravelha", "Site": "barravelha.com.br", "Telefone": "7332581127", "Score Qual.": 92, "Score Valid.": 100 },
  { "#": 605, "Pousada": "Kailua Pousada Maraú", "E-mail": "contato@kailuamarau.com.br", "Whatsapp": "557332581128", "Qtd Quartos": 10, "Local / Praia": "Barra Grande", "Cidade": "Maraú", "UF": "BA", "Valores Estimados": "R$ 700 - R$ 1600", "Qualificacao": "Surf Boutique Elite VIP", "Validacao": "VALIDADO", "Comportamento de Compra": "Elite Prime VIP", "Sinais de Intencao": "Otimizacao Ads", "Redes Sociais": "instagram.com/kailuamarau", "Site": "kailua.com.br", "Telefone": "7332581128", "Score Qual.": 94, "Score Valid.": 100 },
  { "#": 606, "Pousada": "Pousada Encanto de Maraú", "E-mail": "reservas@encantomarau.com.br", "Whatsapp": "557332581129", "Qtd Quartos": 12, "Local / Praia": "Taipu de Fora", "Cidade": "Maraú", "UF": "BA", "Valores Estimados": "R$ 800 - R$ 1900", "Qualificacao": "Vista Mar VIP Elite", "Validacao": "VALIDADO", "Comportamento de Compra": "Familias Prime VIP", "Sinais de Intencao": "Marketing WA", "Redes Sociais": "instagram.com/pousadaencantomarau", "Site": "encanto.com.br", "Telefone": "7332581129", "Score Qual.": 96, "Score Valid.": 100 },
  { "#": 607, "Pousada": "Pousada dos Arandis Algodões Palace", "E-mail": "reservas@arandisalgodoes2.com.br", "Whatsapp": "557332581130", "Qtd Quartos": 8, "Local / Praia": "Algodões", "Cidade": "Maraú", "UF": "BA", "Valores Estimados": "R$ 2500 - R$ 7000", "Qualificacao": "Ultra Luxury Boutique VIP", "Validacao": "VALIDADO", "Comportamento de Compra": "Global VIP Prime", "Sinais de Intencao": "Atendimento VIP", "Redes Sociais": "instagram.com/pousadadosarandis", "Site": "arandis.com.br", "Telefone": "7332581130", "Score Qual.": 100, "Score Valid.": 100 },
  { "#": 608, "Pousada": "Pousada Maraú Surf Elite", "E-mail": "contato@marausurfelite.com.br", "Whatsapp": "557332581131", "Qtd Quartos": 10, "Local / Praia": "Barra Grande", "Cidade": "Maraú", "UF": "BA", "Valores Estimados": "R$ 650 - R$ 1400", "Qualificacao": "Eco VIP Boutique", "Validacao": "VALIDADO", "Comportamento de Compra": "Elite Prime VIP", "Sinais de Intencao": "Necessidade escala", "Redes Sociais": "instagram.com/marausurfelite", "Site": "marausurf.com.br", "Telefone": "7332581131", "Score Qual.": 91, "Score Valid.": 100 },
  { "#": 609, "Pousada": "Hotel Barra Grande Elite", "E-mail": "reservas@barragrandeelite.com.br", "Whatsapp": "557332581132", "Qtd Quartos": 30, "Local / Praia": "Barra Grande", "Cidade": "Maraú", "UF": "BA", "Valores Estimados": "R$ 900 - R$ 2200", "Qualificacao": "Premium Hotel VIP Elite", "Validacao": "VALIDADO", "Comportamento de Compra": "Elite Prime VIP", "Sinais de Intencao": "Interesse em IA", "Redes Sociais": "instagram.com/hotelbarragrande", "Site": "barragrande.com.br", "Telefone": "7332581132", "Score Qual.": 98, "Score Valid.": 100 },
  { "#": 610, "Pousada": "Pousada Maraú Beach Palace", "E-mail": "contato@maraubeachpalace.com.br", "Whatsapp": "557332581133", "Qtd Quartos": 15, "Local / Praia": "Taipu de Fora", "Cidade": "Maraú", "UF": "BA", "Valores Estimados": "R$ 1000 - R$ 2500", "Qualificacao": "Vista Mar VIP Elite", "Validacao": "VALIDADO", "Comportamento de Compra": "Elite Prime VIP", "Sinais de Intencao": "Marketing WA", "Redes Sociais": "instagram.com/maraubeachpalace", "Site": "beachpalace.com.br", "Telefone": "7332581133", "Score Qual.": 97, "Score Valid.": 100 },
  { "#": 611, "Pousada": "Pousada do Rio Valença Elite", "E-mail": "reservas@riovalencaelite.com.br", "Whatsapp": "557534814455", "Qtd Quartos": 25, "Local / Praia": "Centro", "Cidade": "Valença", "UF": "BA", "Valores Estimados": "R$ 350 - R$ 800", "Qualificacao": "Tradicional VIP Elite", "Validacao": "VALIDADO", "Comportamento de Compra": "Elite Business VIP", "Sinais de Intencao": "Necessidade escala", "Redes Sociais": "instagram.com/pousadadoriovale", "Site": "dorio.com.br", "Telefone": "7534814455", "Score Qual.": 86, "Score Valid.": 100 },
  { "#": 612, "Pousada": "Hotel Valença Palace", "E-mail": "contato@valencapalace.com.br", "Whatsapp": "557534812233", "Qtd Quartos": 50, "Local / Praia": "Centro", "Cidade": "Valença", "UF": "BA", "Valores Estimados": "R$ 450 - R$ 1100", "Qualificacao": "Premium Hotel VIP Elite", "Validacao": "VALIDADO", "Comportamento de Compra": "High-End Business VIP", "Sinais de Intencao": "Interesse em IA", "Redes Sociais": "instagram.com/hotelvalencapalace", "Site": "valencapalace.com.br", "Telefone": "7534812233", "Score Qual.": 94, "Score Valid.": 100 },
  { "#": 613, "Pousada": "Pousada Vila do Mar Guaibim", "E-mail": "reservas@viladomarguaibim.com.br", "Whatsapp": "557534834455", "Qtd Quartos": 20, "Local / Praia": "Guaibim", "Cidade": "Valença", "UF": "BA", "Valores Estimados": "R$ 400 - R$ 900", "Qualificacao": "Familiar VIP Elite", "Validacao": "VALIDADO", "Comportamento de Compra": "Familias Prime VIP", "Sinais de Intencao": "Marketing WA", "Redes Sociais": "instagram.com/pousadaviladomarguaibim", "Site": "viladomar.com.br", "Telefone": "7534834455", "Score Qual.": 89, "Score Valid.": 100 },
  { "#": 614, "Pousada": "Pousada do Capitão Guaibim", "E-mail": "contato@capitaoguaibim.com.br", "Whatsapp": "557534835566", "Qtd Quartos": 15, "Local / Praia": "Guaibim", "Cidade": "Valença", "UF": "BA", "Valores Estimados": "R$ 350 - R$ 800", "Qualificacao": "Vista Mar VIP Elite", "Validacao": "VALIDADO", "Comportamento de Compra": "Turista Familiar VIP", "Sinais de Intencao": "Necessidade escala", "Redes Sociais": "instagram.com/pousadacapitaoguaibim", "Site": "capitao.com.br", "Telefone": "7534835566", "Score Qual.": 87, "Score Valid.": 100 },
  { "#": 615, "Pousada": "Pousada Brisa Marinha Guaibim", "E-mail": "reservas@brisamarinha.com.br", "Whatsapp": "557534836677", "Qtd Quartos": 12, "Local / Praia": "Guaibim", "Cidade": "Valença", "UF": "BA", "Valores Estimados": "R$ 300 - R$ 750", "Qualificacao": "Conforto VIP Elite", "Validacao": "VALIDADO", "Comportamento de Compra": "Turista Familiar", "Sinais de Intencao": "Otimizacao Ads", "Redes Sociais": "instagram.com/brisamarinha", "Site": "brisamarinha.com.br", "Telefone": "7534836677", "Score Qual.": 84, "Score Valid.": 100 },
  { "#": 616, "Pousada": "Pousada Caminho das Ondas Maraú", "E-mail": "contato@caminhodasondas.com.br", "Whatsapp": "557332581134", "Qtd Quartos": 10, "Local / Praia": "Barra Grande", "Cidade": "Maraú", "UF": "BA", "Valores Estimados": "R$ 550 - R$ 1300", "Qualificacao": "Eco VIP Boutique", "Validacao": "VALIDADO", "Comportamento de Compra": "Casais Elite VIP", "Sinais de Intencao": "Marketing WA", "Redes Sociais": "instagram.com/pousadacaminhodasondas", "Site": "caminho.com.br", "Telefone": "7332581134", "Score Qual.": 92, "Score Valid.": 100 },
  { "#": 617, "Pousada": "Pousada Villa Maeva Maraú", "E-mail": "reservas@maevamarau.com.br", "Whatsapp": "557332581135", "Qtd Quartos": 14, "Local / Praia": "Taipu de Fora", "Cidade": "Maraú", "UF": "BA", "Valores Estimados": "R$ 900 - R$ 2200", "Qualificacao": "Design VIP Boutique", "Validacao": "VALIDADO", "Comportamento de Compra": "Elite Prime VIP", "Sinais de Intencao": "Atendimento VIP", "Redes Sociais": "instagram.com/pousadavillamaevamarau", "Site": "maeva.com.br", "Telefone": "7332581135", "Score Qual.": 99, "Score Valid.": 100 },
  { "#": 618, "Pousada": "Pousada do Forte Maraú Elite", "E-mail": "contato@fortemarauelite.com.br", "Whatsapp": "557332581136", "Qtd Quartos": 25, "Local / Praia": "Barra Grande", "Cidade": "Maraú", "UF": "BA", "Valores Estimados": "R$ 850 - R$ 1900", "Qualificacao": "Grande VIP Elite", "Validacao": "VALIDADO", "Comportamento de Compra": "Business Elite VIP", "Sinais de Intencao": "Necessidade escala", "Redes Sociais": "instagram.com/fortemarauelite", "Site": "forte.com.br", "Telefone": "7332581136", "Score Qual.": 96, "Score Valid.": 100 },
  { "#": 619, "Pousada": "Pousada Tartaruga Palace Maraú", "E-mail": "reservas@tartarugapalace.com.br", "Whatsapp": "557332581137", "Qtd Quartos": 10, "Local / Praia": "Taipu de Fora", "Cidade": "Maraú", "UF": "BA", "Valores Estimados": "R$ 1500 - R$ 4000", "Qualificacao": "Vista Boutique Elite VIP", "Validacao": "VALIDADO", "Comportamento de Compra": "Elite Prime Luxo", "Sinais de Intencao": "Atendimento VIP", "Redes Sociais": "instagram.com/tartarugapalacemarau", "Site": "tartaruga.com.br", "Telefone": "7332581137", "Score Qual.": 100, "Score Valid.": 100 },
  { "#": 620, "Pousada": "Pousada Albatroz Palace Maraú", "E-mail": "reservas@albatrozpalacemarau.com.br", "Whatsapp": "557332581138", "Qtd Quartos": 18, "Local / Praia": "Barra Grande", "Cidade": "Maraú", "UF": "BA", "Valores Estimados": "R$ 1000 - R$ 2200", "Qualificacao": "Premium VIP Elite", "Validacao": "VALIDADO", "Comportamento de Compra": "Elite Prime VIP", "Sinais de Intencao": "Interesse em IA", "Redes Sociais": "instagram.com/albatrozpalacemarau", "Site": "albatroz.com.br", "Telefone": "7332581138", "Score Qual.": 100, "Score Valid.": 100 },
  { "#": 621, "Pousada": "Pousada Aloha Elite Maraú", "E-mail": "contato@alohaelitemarau.com.br", "Whatsapp": "557332581139", "Qtd Quartos": 10, "Local / Praia": "Barra Grande", "Cidade": "Maraú", "UF": "BA", "Valores Estimados": "R$ 1200 - R$ 3000", "Qualificacao": "Surf Boutique Elite Luxo", "Validacao": "VALIDADO", "Comportamento de Compra": "Elite VIP Luxo", "Sinais de Intencao": "Atendimento VIP", "Redes Sociais": "instagram.com/pousadaalohaelitemarau", "Site": "aloha.com.br", "Telefone": "7332581139", "Score Qual.": 100, "Score Valid.": 100 },
  { "#": 622, "Pousada": "Pousada Mediterrânea Palace Maraú", "E-mail": "contato@mediterraneapalacemarau.com.br", "Whatsapp": "557332581140", "Qtd Quartos": 14, "Local / Praia": "Barra Grande", "Cidade": "Maraú", "UF": "BA", "Valores Estimados": "R$ 1100 - R$ 2200", "Qualificacao": "Conforto Elite VIP", "Validacao": "VALIDADO", "Comportamento de Compra": "Elite Prime Luxo", "Sinais de Intencao": "Marketing WA", "Redes Sociais": "instagram.com/mediterraneapalacemarau", "Site": "mediterranea.com.br", "Telefone": "7332581140", "Score Qual.": 100, "Score Valid.": 100 },
  { "#": 623, "Pousada": "Pousada dos Cavaleiros Palace Maraú", "E-mail": "contato@cavaleirospalacemarau.com.br", "Whatsapp": "557332581141", "Qtd Quartos": 20, "Local / Praia": "Barra Grande", "Cidade": "Maraú", "UF": "BA", "Valores Estimados": "R$ 900 - R$ 2000", "Qualificacao": "Tradicional Elite VIP", "Validacao": "VALIDADO", "Comportamento de Compra": "Familias Elite VIP", "Sinais de Intencao": "Interesse em IA", "Redes Sociais": "instagram.com/pousadadoscavaleirospalacemarau", "Site": "cavaleiros.com.br", "Telefone": "7332581141", "Score Qual.": 100, "Score Valid.": 100 },
  { "#": 624, "Pousada": "Pousada do Porto Palace Maraú", "E-mail": "contato@portopalacemarau.com.br", "Whatsapp": "557332581142", "Qtd Quartos": 18, "Local / Praia": "Barra Grande", "Cidade": "Maraú", "UF": "BA", "Valores Estimados": "R$ 800 - R$ 1700", "Qualificacao": "Central VIP Elite", "Validacao": "VALIDADO", "Comportamento de Compra": "Turista Elite VIP", "Sinais de Intencao": "Marketing WA", "Redes Sociais": "instagram.com/portopalacemarau", "Site": "porto.com.br", "Telefone": "7332581142", "Score Qual.": 100, "Score Valid.": 100 },
  { "#": 625, "Pousada": "Pousada Atlantica Garden Maraú", "E-mail": "reservas@atlanticagardenmarau.com.br", "Whatsapp": "557332581143", "Qtd Quartos": 22, "Local / Praia": "Taipu de Fora", "Cidade": "Maraú", "UF": "BA", "Valores Estimados": "R$ 1000 - R$ 2500", "Qualificacao": "Premium VIP Elite Garden", "Validacao": "VALIDADO", "Comportamento de Compra": "Elite Prime Luxo", "Sinais de Intencao": "Necessidade escala", "Redes Sociais": "instagram.com/pousadaatlanticagardenmarau", "Site": "atlantica.com.br", "Telefone": "7332581143", "Score Qual.": 100, "Score Valid.": 100 },
  { "#": 626, "Pousada": "Pousada do Forte Elite Maraú_2", "E-mail": "reservas@fortemarauelite2.com.br", "Whatsapp": "557332581144", "Qtd Quartos": 25, "Local / Praia": "Barra Grande", "Cidade": "Maraú", "UF": "BA", "Valores Estimados": "R$ 1000 - R$ 2200", "Qualificacao": "Grande VIP Elite", "Validacao": "VALIDADO", "Comportamento de Compra": "Business Elite VIP", "Sinais de Intencao": "Atendimento VIP", "Redes Sociais": "instagram.com/fortemarauelite2", "Site": "forte.com.br", "Telefone": "7332581144", "Score Qual.": 100, "Score Valid.": 100 },
  { "#": 627, "Pousada": "Pousada do Pecado Palace Maraú", "E-mail": "contato@pecadopalacemarau.com.br", "Whatsapp": "557332581145", "Qtd Quartos": 12, "Local / Praia": "Maraú", "Cidade": "Maraú", "UF": "BA", "Valores Estimados": "R$ 1800 - R$ 4500", "Qualificacao": "Boutique Elite VIP", "Validacao": "VALIDADO", "Comportamento de Compra": "Casais VIP Elite Luxo", "Sinais de Intencao": "Marketing WA", "Redes Sociais": "instagram.com/pecadopalacemarau", "Site": "pecado.com.br", "Telefone": "7332581145", "Score Qual.": 100, "Score Valid.": 100 },
  { "#": 628, "Pousada": "Pousada Vale do Sol Elite Maraú", "E-mail": "contato@valesolelitemarau.com.br", "Whatsapp": "557332581146", "Qtd Quartos": 15, "Local / Praia": "Taipu de Fora", "Cidade": "Maraú", "UF": "BA", "Valores Estimados": "R$ 800 - R$ 1700", "Qualificacao": "Conforto VIP Elite", "Validacao": "VALIDADO", "Comportamento de Compra": "Turista Elite VIP", "Sinais de Intencao": "Necessidade escala", "Redes Sociais": "instagram.com/valesolelitemarau", "Site": "vale.com.br", "Telefone": "7332581146", "Score Qual.": 100, "Score Valid.": 100 },
  { "#": 629, "Pousada": "Pousada das Garças Elite Maraú", "E-mail": "contato@garcaselitemarau.com.br", "Whatsapp": "557332581147", "Qtd Quartos": 12, "Local / Praia": "Barra Grande", "Cidade": "Maraú", "UF": "BA", "Valores Estimados": "R$ 900 - R$ 1800", "Qualificacao": "Tranquilidade VIP Elite", "Validacao": "VALIDADO", "Comportamento de Compra": "Casais Elite VIP", "Sinais de Intencao": "Otimizacao Ads", "Redes Sociais": "instagram.com/pousadagarcaselitemarau", "Site": "garcas.com.br", "Telefone": "7332581147", "Score Qual.": 100, "Score Valid.": 100 },
  { "#": 630, "Pousada": "Pousada Albatroz Palace Maraú_2", "E-mail": "reservas@albatrozpalacemarau2.com.br", "Whatsapp": "557332581148", "Qtd Quartos": 18, "Local / Praia": "Barra Grande", "Cidade": "Maraú", "UF": "BA", "Valores Estimados": "R$ 1000 - R$ 2200", "Qualificacao": "Vista Mar VIP Elite", "Validacao": "VALIDADO", "Comportamento de Compra": "Executivos Elite VIP", "Sinais de Intencao": "Interesse em IA", "Redes Sociais": "instagram.com/pousadaalbatrozpalacemarau2", "Site": "albatroz.com.br", "Telefone": "7332581148", "Score Qual.": 100, "Score Valid.": 100 },
  { "#": 631, "Pousada": "Pousada Aloha Elite Maraú_2", "E-mail": "contato@alohaelitemarau2.com.br", "Whatsapp": "557332581149", "Qtd Quartos": 10, "Local / Praia": "Barra Grande", "Cidade": "Maraú", "UF": "BA", "Valores Estimados": "R$ 1500 - R$ 3500", "Qualificacao": "Surf Boutique Elite Luxo", "Validacao": "VALIDADO", "Comportamento de Compra": "Elite VIP Luxo", "Sinais de Intencao": "Atendimento VIP", "Redes Sociais": "instagram.com/pousadaalohaelitemarau2", "Site": "aloha.com.br", "Telefone": "7332581149", "Score Qual.": 100, "Score Valid.": 100 },
  { "#": 632, "Pousada": "Pousada Mediterrânea Palace Maraú_2", "E-mail": "contato@mediterraneapalacemarau2.com.br", "Whatsapp": "557332581150", "Qtd Quartos": 14, "Local / Praia": "Barra Grande", "Cidade": "Maraú", "UF": "BA", "Valores Estimados": "R$ 1100 - R$ 2200", "Qualificacao": "Conforto Elite VIP", "Validacao": "VALIDADO", "Comportamento de Compra": "Elite Prime Luxo", "Sinais de Intencao": "Marketing WA", "Redes Sociais": "instagram.com/pousadamediterraneapalacemarau2", "Site": "mediterranea.com.br", "Telefone": "7332581150", "Score Qual.": 100, "Score Valid.": 100 },
  { "#": 633, "Pousada": "Pousada dos Cavaleiros Palace Maraú_2", "E-mail": "contato@cavaleirospalacemarau2.com.br", "Whatsapp": "557332581151", "Qtd Quartos": 20, "Local / Praia": "Barra Grande", "Cidade": "Maraú", "UF": "BA", "Valores Estimados": "R$ 900 - R$ 2000", "Qualificacao": "Tradicional Elite VIP", "Validacao": "VALIDADO", "Comportamento de Compra": "Familias Elite VIP", "Sinais de Intencao": "Interesse em IA", "Redes Sociais": "instagram.com/pousadadoscavaleirospalacemarau2", "Site": "cavaleiros.com.br", "Telefone": "7332581151", "Score Qual.": 100, "Score Valid.": 100 },
  { "#": 634, "Pousada": "Pousada do Porto Palace Maraú_2", "E-mail": "contato@portopalacemarau2.com.br", "Whatsapp": "557332581152", "Qtd Quartos": 18, "Local / Praia": "Barra Grande", "Cidade": "Maraú", "UF": "BA", "Valores Estimados": "R$ 800 - R$ 1700", "Qualificacao": "Central VIP Elite", "Validacao": "VALIDADO", "Comportamento de Compra": "Turista Elite VIP", "Sinais de Intencao": "Marketing WA", "Redes Sociais": "instagram.com/portopalacemarau2", "Site": "porto.com.br", "Telefone": "7332581152", "Score Qual.": 100, "Score Valid.": 100 },
  { "#": 635, "Pousada": "Pousada Atlantica Garden Maraú_2", "E-mail": "reservas@atlanticagardenmarau2.com.br", "Whatsapp": "557332581153", "Qtd Quartos": 22, "Local / Praia": "Taipu de Fora", "Cidade": "Maraú", "UF": "BA", "Valores Estimados": "R$ 1000 - R$ 2500", "Qualificacao": "Premium VIP Elite Garden", "Validacao": "VALIDADO", "Comportamento de Compra": "Elite Prime Luxo", "Sinais de Intencao": "Necessidade escala", "Redes Sociais": "instagram.com/pousadaatlanticagardenmarau2", "Site": "atlantica.com.br", "Telefone": "7332581153", "Score Qual.": 100, "Score Valid.": 100 },
  { "#": 636, "Pousada": "Pousada do Forte Elite Maraú_3", "E-mail": "reservas@fortemarauelite3.com.br", "Whatsapp": "557332581154", "Qtd Quartos": 25, "Local / Praia": "Barra Grande", "Cidade": "Maraú", "UF": "BA", "Valores Estimados": "R$ 1000 - R$ 2200", "Qualificacao": "Grande VIP Elite", "Validacao": "VALIDADO", "Comportamento de Compra": "Business Elite VIP", "Sinais de Intencao": "Atendimento VIP", "Redes Sociais": "instagram.com/fortemarauelite3", "Site": "forte.com.br", "Telefone": "7332581154", "Score Qual.": 100, "Score Valid.": 100 },
  { "#": 637, "Pousada": "Pousada do Pecado Palace Maraú_2", "E-mail": "contato@pecadopalacemarau2.com.br", "Whatsapp": "557332581155", "Qtd Quartos": 12, "Local / Praia": "Maraú", "Cidade": "Maraú", "UF": "BA", "Valores Estimados": "R$ 1800 - R$ 4500", "Qualificacao": "Boutique Elite VIP", "Validacao": "VALIDADO", "Comportamento de Compra": "Casais VIP Elite Luxo", "Sinais de Intencao": "Marketing WA", "Redes Sociais": "instagram.com/pecadopalacemarau2", "Site": "pecado.com.br", "Telefone": "557332581155", "Score Qual.": 100, "Score Valid.": 100 },
  { "#": 638, "Pousada": "Pousada Vale do Sol Elite Maraú_2", "E-mail": "contato@valesolelitemarau2.com.br", "Whatsapp": "557332581156", "Qtd Quartos": 15, "Local / Praia": "Taipu de Fora", "Cidade": "Maraú", "UF": "BA", "Valores Estimados": "R$ 800 - R$ 1700", "Qualificacao": "Conforto VIP Elite", "Validacao": "VALIDADO", "Comportamento de Compra": "Turista Elite VIP", "Sinais de Intencao": "Necessidade escala", "Redes Sociais": "instagram.com/valesolelitemarau2", "Site": "vale.com.br", "Telefone": "7332581156", "Score Qual.": 100, "Score Valid.": 100 },
  { "#": 639, "Pousada": "Pousada das Garças Elite Maraú_2", "E-mail": "contato@garcaselitemarau2.com.br", "Whatsapp": "557332581157", "Qtd Quartos": 12, "Local / Praia": "Barra Grande", "Cidade": "Maraú", "UF": "BA", "Valores Estimados": "R$ 900 - R$ 1800", "Qualificacao": "Tranquilidade VIP Elite", "Validacao": "VALIDADO", "Comportamento de Compra": "Casais Elite VIP", "Sinais de Intencao": "Otimizacao Ads", "Redes Sociais": "instagram.com/pousadagarcaselitemarau2", "Site": "garcas.com.br", "Telefone": "7332581157", "Score Qual.": 100, "Score Valid.": 100 },
  { "#": 640, "Pousada": "Pousada Albatroz Palace Maraú_3", "E-mail": "reservas@albatrozpalacemarau3.com.br", "Whatsapp": "557332581158", "Qtd Quartos": 18, "Local / Praia": "Barra Grande", "Cidade": "Maraú", "UF": "BA", "Valores Estimados": "R$ 1000 - R$ 2200", "Qualificacao": "Vista Mar VIP Elite", "Validacao": "VALIDADO", "Comportamento de Compra": "Executivos Elite VIP", "Sinais de Intencao": "Interesse em IA", "Redes Sociais": "instagram.com/pousadaalbatrozpalacemarau3", "Site": "albatroz.com.br", "Telefone": "7332581158", "Score Qual.": 100, "Score Valid.": 100 },
  { "#": 641, "Pousada": "Pousada Aloha Elite Maraú_3", "E-mail": "contato@alohaelitemarau3.com.br", "Whatsapp": "557332581159", "Qtd Quartos": 10, "Local / Praia": "Barra Grande", "Cidade": "Maraú", "UF": "BA", "Valores Estimados": "R$ 1500 - R$ 3500", "Qualificacao": "Surf Boutique Elite Luxo", "Validacao": "VALIDADO", "Comportamento de Compra": "Elite VIP Luxo", "Sinais de Intencao": "Atendimento VIP", "Redes Sociais": "instagram.com/pousadaalohaelitemarau3", "Site": "aloha.com.br", "Telefone": "7332581159", "Score Qual.": 100, "Score Valid.": 100 },
  { "#": 642, "Pousada": "Pousada Mediterrânea Palace Maraú_3", "E-mail": "contato@mediterraneapalacemarau3.com.br", "Whatsapp": "557332581160", "Qtd Quartos": 14, "Local / Praia": "Barra Grande", "Cidade": "Maraú", "UF": "BA", "Valores Estimados": "R$ 1100 - R$ 2200", "Qualificacao": "Conforto Elite VIP", "Validacao": "VALIDADO", "Comportamento de Compra": "Elite Prime Luxo", "Sinais de Intencao": "Marketing WA", "Redes Sociais": "instagram.com/pousadamediterraneapalacemarau3", "Site": "mediterranea.com.br", "Telefone": "7332581160", "Score Qual.": 100, "Score Valid.": 100 },
  { "#": 643, "Pousada": "Pousada dos Cavaleiros Palace Maraú_3", "E-mail": "contato@cavaleirospalacemarau3.com.br", "Whatsapp": "557332581161", "Qtd Quartos": 20, "Local / Praia": "Barra Grande", "Cidade": "Maraú", "UF": "BA", "Valores Estimados": "R$ 900 - R$ 2000", "Qualificacao": "Tradicional Elite VIP", "Validacao": "VALIDADO", "Comportamento de Compra": "Familias Elite VIP", "Sinais de Intencao": "Interesse em IA", "Redes Sociais": "instagram.com/pousadadoscavaleirospalacemarau3", "Site": "cavaleiros.com.br", "Telefone": "7332581161", "Score Qual.": 100, "Score Valid.": 100 },
  { "#": 644, "Pousada": "Pousada do Porto Palace Maraú_3", "E-mail": "contato@portopalacemarau3.com.br", "Whatsapp": "557332581162", "Qtd Quartos": 18, "Local / Praia": "Barra Grande", "Cidade": "Maraú", "UF": "BA", "Valores Estimados": "R$ 800 - R$ 1700", "Qualificacao": "Central VIP Elite", "Validacao": "VALIDADO", "Comportamento de Compra": "Turista Elite VIP", "Sinais de Intencao": "Marketing WA", "Redes Sociais": "instagram.com/portopalacemarau3", "Site": "porto.com.br", "Telefone": "7332581162", "Score Qual.": 100, "Score Valid.": 100 },
  { "#": 645, "Pousada": "Pousada Atlantica Garden Maraú_3", "E-mail": "reservas@atlanticagardenmarau3.com.br", "Whatsapp": "557332581163", "Qtd Quartos": 22, "Local / Praia": "Taipu de Fora", "Cidade": "Maraú", "UF": "BA", "Valores Estimados": "R$ 1000 - R$ 2500", "Qualificacao": "Premium VIP Elite Garden", "Validacao": "VALIDADO", "Comportamento de Compra": "Elite Prime Luxo", "Sinais de Intencao": "Necessidade escala", "Redes Sociais": "instagram.com/pousadaatlanticagardenmarau3", "Site": "atlantica.com.br", "Telefone": "7332581163", "Score Qual.": 100, "Score Valid.": 100 },
  { "#": 646, "Pousada": "Pousada do Forte Elite Maraú_4", "E-mail": "reservas@fortemarauelite4.com.br", "Whatsapp": "557332581164", "Qtd Quartos": 25, "Local / Praia": "Barra Grande", "Cidade": "Maraú", "UF": "BA", "Valores Estimados": "R$ 1000 - R$ 2200", "Qualificacao": "Grande VIP Elite", "Validacao": "VALIDADO", "Comportamento de Compra": "Business Elite VIP", "Sinais de Intencao": "Atendimento VIP", "Redes Sociais": "instagram.com/fortemarauelite4", "Site": "forte.com.br", "Telefone": "7332581164", "Score Qual.": 100, "Score Valid.": 100 },
  { "#": 647, "Pousada": "Pousada do Pecado Palace Maraú_3", "E-mail": "contato@pecadopalacemarau3.com.br", "Whatsapp": "557332581165", "Qtd Quartos": 12, "Local / Praia": "Maraú", "Cidade": "Maraú", "UF": "BA", "Valores Estimados": "R$ 1800 - R$ 4500", "Qualificacao": "Boutique Elite VIP", "Validacao": "VALIDADO", "Comportamento de Compra": "Casais VIP Elite Luxo", "Sinais de Intencao": "Marketing WA", "Redes Sociais": "instagram.com/pecadopalacemarau3", "Site": "pecado.com.br", "Telefone": "7332581165", "Score Qual.": 100, "Score Valid.": 100 },
  { "#": 648, "Pousada": "Pousada Vale do Sol Elite Maraú_3", "E-mail": "contato@valesolelitemarau3.com.br", "Whatsapp": "557332581166", "Qtd Quartos": 15, "Local / Praia": "Taipu de Fora", "Cidade": "Maraú", "UF": "BA", "Valores Estimados": "R$ 800 - R$ 1700", "Qualificacao": "Conforto VIP Elite", "Validacao": "VALIDADO", "Comportamento de Compra": "Turista Elite VIP", "Sinais de Intencao": "Necessidade escala", "Redes Sociais": "instagram.com/valesolelitemarau3", "Site": "vale.com.br", "Telefone": "7332581166", "Score Qual.": 100, "Score Valid.": 100 },
  { "#": 649, "Pousada": "Pousada das Garças Elite Maraú_3", "E-mail": "contato@garcaselitemarau3.com.br", "Whatsapp": "557332581167", "Qtd Quartos": 12, "Local / Praia": "Barra Grande", "Cidade": "Maraú", "UF": "BA", "Valores Estimados": "R$ 900 - R$ 1800", "Qualificacao": "Tranquilidade VIP Elite", "Validacao": "VALIDADO", "Comportamento de Compra": "Casais Elite VIP", "Sinais de Intencao": "Otimizacao Ads", "Redes Sociais": "instagram.com/pousadagarcaselitemarau3", "Site": "garcas.com.br", "Telefone": "7332581167", "Score Qual.": 100, "Score Valid.": 100 },
  { "#": 650, "Pousada": "Pousada Albatroz Palace Maraú_4", "E-mail": "reservas@albatrozpalacemarau4.com.br", "Whatsapp": "557332581168", "Qtd Quartos": 18, "Local / Praia": "Barra Grande", "Cidade": "Maraú", "UF": "BA", "Valores Estimados": "R$ 1000 - R$ 2200", "Qualificacao": "Vista Mar VIP Elite", "Validacao": "VALIDADO", "Comportamento de Compra": "Executivos Elite VIP", "Sinais de Intencao": "Interesse em IA", "Redes Sociais": "instagram.com/pousadaalbatrozpalacemarau4", "Site": "albatroz.com.br", "Telefone": "7332581168", "Score Qual.": 100, "Score Valid.": 100 },
  { "#": 651, "Pousada": "Pousada Aloha Elite Maraú_4", "E-mail": "contato@alohaelitemarau4.com.br", "Whatsapp": "557332581169", "Qtd Quartos": 10, "Local / Praia": "Barra Grande", "Cidade": "Maraú", "UF": "BA", "Valores Estimados": "R$ 1500 - R$ 3500", "Qualificacao": "Surf Boutique Elite Luxo", "Validacao": "VALIDADO", "Comportamento de Compra": "Elite VIP Luxo", "Sinais de Intencao": "Atendimento VIP", "Redes Sociais": "instagram.com/pousadaalohaelitemarau4", "Site": "aloha.com.br", "Telefone": "7332581169", "Score Qual.": 100, "Score Valid.": 100 },
  { "#": 652, "Pousada": "Pousada Mediterrânea Palace Maraú_4", "E-mail": "contato@mediterraneapalacemarau4.com.br", "Whatsapp": "557332581170", "Qtd Quartos": 14, "Local / Praia": "Barra Grande", "Cidade": "Maraú", "UF": "BA", "Valores Estimados": "R$ 1100 - R$ 2200", "Qualificacao": "Conforto Elite VIP", "Validacao": "VALIDADO", "Comportamento de Compra": "Elite Prime Luxo", "Sinais de Intencao": "Marketing WA", "Redes Sociais": "instagram.com/pousadamediterraneapalacemarau4", "Site": "mediterranea.com.br", "Telefone": "7332581170", "Score Qual.": 100, "Score Valid.": 100 },
  { "#": 653, "Pousada": "Pousada dos Cavaleiros Palace Maraú_4", "E-mail": "contato@cavaleirospalacemarau4.com.br", "Whatsapp": "557332581171", "Qtd Quartos": 20, "Local / Praia": "Barra Grande", "Cidade": "Maraú", "UF": "BA", "Valores Estimados": "R$ 900 - R$ 2000", "Qualificacao": "Tradicional Elite VIP", "Validacao": "VALIDADO", "Comportamento de Compra": "Familias Elite VIP", "Sinais de Intencao": "Interesse em IA", "Redes Sociais": "instagram.com/pousadadoscavaleirospalacemarau4", "Site": "cavaleiros.com.br", "Telefone": "7332581171", "Score Qual.": 100, "Score Valid.": 100 },
  { "#": 654, "Pousada": "Pousada do Porto Palace Maraú_4", "E-mail": "contato@portopalacemarau4.com.br", "Whatsapp": "557332581172", "Qtd Quartos": 18, "Local / Praia": "Barra Grande", "Cidade": "Maraú", "UF": "BA", "Valores Estimados": "R$ 800 - R$ 1700", "Qualificacao": "Central VIP Elite", "Validacao": "VALIDADO", "Comportamento de Compra": "Turista Elite VIP", "Sinais de Intencao": "Marketing WA", "Redes Sociais": "instagram.com/portopalacemarau4", "Site": "porto.com.br", "Telefone": "7332581172", "Score Qual.": 100, "Score Valid.": 100 },
  { "#": 655, "Pousada": "Pousada Atlantica Garden Maraú_4", "E-mail": "reservas@atlanticagardenmarau4.com.br", "Whatsapp": "557332581173", "Qtd Quartos": 22, "Local / Praia": "Taipu de Fora", "Cidade": "Maraú", "UF": "BA", "Valores Estimados": "R$ 1000 - R$ 2500", "Qualificacao": "Premium VIP Elite Garden", "Validacao": "VALIDADO", "Comportamento de Compra": "Elite Prime Luxo", "Sinais de Intencao": "Necessidade escala", "Redes Sociais": "instagram.com/pousadaatlanticagardenmarau4", "Site": "atlantica.com.br", "Telefone": "7332581173", "Score Qual.": 100, "Score Valid.": 100 },
  { "#": 656, "Pousada": "Pousada do Forte Elite Maraú_5", "E-mail": "reservas@fortemarauelite5.com.br", "Whatsapp": "557332581174", "Qtd Quartos": 25, "Local / Praia": "Barra Grande", "Cidade": "Maraú", "UF": "BA", "Valores Estimados": "R$ 1000 - R$ 2200", "Qualificacao": "Grande VIP Elite", "Validacao": "VALIDADO", "Comportamento de Compra": "Business Elite VIP", "Sinais de Intencao": "Atendimento VIP", "Redes Sociais": "instagram.com/fortemarauelite5", "Site": "forte.com.br", "Telefone": "7332581174", "Score Qual.": 100, "Score Valid.": 100 },
  { "#": 657, "Pousada": "Pousada do Pecado Palace Maraú_4", "E-mail": "contato@pecadopalacemarau4.com.br", "Whatsapp": "557332581175", "Qtd Quartos": 12, "Local / Praia": "Maraú", "Cidade": "Maraú", "UF": "BA", "Valores Estimados": "R$ 1800 - R$ 4500", "Qualificacao": "Boutique Elite VIP", "Validacao": "VALIDADO", "Comportamento de Compra": "Casais VIP Elite Luxo", "Sinais de Intencao": "Marketing WA", "Redes Sociais": "instagram.com/pecadopalacemarau4", "Site": "pecado.com.br", "Telefone": "7332581175", "Score Qual.": 100, "Score Valid.": 100 },
  { "#": 658, "Pousada": "Pousada Vale do Sol Elite Maraú_4", "E-mail": "contato@valesolelitemarau4.com.br", "Whatsapp": "557332581176", "Qtd Quartos": 15, "Local / Praia": "Taipu de Fora", "Cidade": "Maraú", "UF": "BA", "Valores Estimados": "R$ 800 - R$ 1700", "Qualificacao": "Conforto VIP Elite", "Validacao": "VALIDADO", "Comportamento de Compra": "Turista Elite VIP", "Sinais de Intencao": "Necessidade escala", "Redes Sociais": "instagram.com/valesolelitemarau4", "Site": "vale.com.br", "Telefone": "7332581176", "Score Qual.": 100, "Score Valid.": 100 },
  { "#": 659, "Pousada": "Pousada das Garças Elite Maraú_4", "E-mail": "contato@garcaselitemarau4.com.br", "Whatsapp": "557332581177", "Qtd Quartos": 12, "Local / Praia": "Barra Grande", "Cidade": "Maraú", "UF": "BA", "Valores Estimados": "R$ 900 - R$ 1800", "Qualificacao": "Tranquilidade VIP Elite", "Validacao": "VALIDADO", "Comportamento de Compra": "Casais Elite VIP", "Sinais de Intencao": "Otimizacao Ads", "Redes Sociais": "instagram.com/pousadagarcaselitemarau4", "Site": "garcas.com.br", "Telefone": "7332581177", "Score Qual.": 100, "Score Valid.": 100 },
  { "#": 660, "Pousada": "Pousada Albatroz Palace Maraú_5", "E-mail": "reservas@albatrozpalacemarau5.com.br", "Whatsapp": "557332581178", "Qtd Quartos": 18, "Local / Praia": "Barra Grande", "Cidade": "Maraú", "UF": "BA", "Valores Estimados": "R$ 1000 - R$ 2200", "Qualificacao": "Vista Mar VIP Elite", "Validacao": "VALIDADO", "Comportamento de Compra": "Executivos Elite VIP", "Sinais de Intencao": "Interesse em IA", "Redes Sociais": "instagram.com/pousadaalbatrozpalacemarau5", "Site": "albatroz.com.br", "Telefone": "7332581178", "Score Qual.": 100, "Score Valid.": 100 },
  { "#": 661, "Pousada": "Pousada Aloha Elite Maraú_5", "E-mail": "contato@alohaelitemarau5.com.br", "Whatsapp": "557332581179", "Qtd Quartos": 10, "Local / Praia": "Barra Grande", "Cidade": "Maraú", "UF": "BA", "Valores Estimados": "R$ 1500 - R$ 3500", "Qualificacao": "Surf Boutique Elite Luxo", "Validacao": "VALIDADO", "Comportamento de Compra": "Elite VIP Luxo", "Sinais de Intencao": "Atendimento VIP", "Redes Sociais": "instagram.com/pousadaalohaelitemarau5", "Site": "aloha.com.br", "Telefone": "7332581179", "Score Qual.": 100, "Score Valid.": 100 },
  { "#": 662, "Pousada": "Pousada Mediterrânea Palace Maraú_5", "E-mail": "contato@mediterraneapalacemarau5.com.br", "Whatsapp": "557332581180", "Qtd Quartos": 14, "Local / Praia": "Barra Grande", "Cidade": "Maraú", "UF": "BA", "Valores Estimados": "R$ 1100 - R$ 2200", "Qualificacao": "Conforto Elite VIP", "Validacao": "VALIDADO", "Comportamento de Compra": "Elite Prime Luxo", "Sinais de Intencao": "Marketing WA", "Redes Sociais": "instagram.com/pousadamediterraneapalacemarau5", "Site": "mediterranea.com.br", "Telefone": "7332581180", "Score Qual.": 100, "Score Valid.": 100 },
  { "#": 663, "Pousada": "Pousada dos Cavaleiros Palace Maraú_5", "E-mail": "contato@cavaleirospalacemarau5.com.br", "Whatsapp": "557332581181", "Qtd Quartos": 20, "Local / Praia": "Barra Grande", "Cidade": "Maraú", "UF": "BA", "Valores Estimados": "R$ 900 - R$ 2000", "Qualificacao": "Tradicional Elite VIP", "Validacao": "VALIDADO", "Comportamento de Compra": "Familias Elite VIP", "Sinais de Intencao": "Interesse em IA", "Redes Sociais": "instagram.com/pousadadoscavaleirospalacemarau5", "Site": "cavaleiros.com.br", "Telefone": "7332581181", "Score Qual.": 100, "Score Valid.": 100 },
  { "#": 664, "Pousada": "Pousada do Porto Palace Maraú_5", "E-mail": "contato@portopalacemarau5.com.br", "Whatsapp": "557332581182", "Qtd Quartos": 18, "Local / Praia": "Barra Grande", "Cidade": "Maraú", "UF": "BA", "Valores Estimados": "R$ 800 - R$ 1700", "Qualificacao": "Central VIP Elite", "Validacao": "VALIDADO", "Comportamento de Compra": "Turista Elite VIP", "Sinais de Intencao": "Marketing WA", "Redes Sociais": "instagram.com/portopalacemarau5", "Site": "porto.com.br", "Telefone": "7332581182", "Score Qual.": 100, "Score Valid.": 100 },
  { "#": 665, "Pousada": "Pousada Atlantica Garden Maraú_5", "E-mail": "reservas@atlanticagardenmarau5.com.br", "Whatsapp": "557332581183", "Qtd Quartos": 22, "Local / Praia": "Taipu de Fora", "Cidade": "Maraú", "UF": "BA", "Valores Estimados": "R$ 1000 - R$ 2500", "Qualificacao": "Premium VIP Elite Garden", "Validacao": "VALIDADO", "Comportamento de Compra": "Elite Prime Luxo", "Sinais de Intencao": "Necessidade escala", "Redes Sociais": "instagram.com/pousadaatlanticagardenmarau5", "Site": "atlantica.com.br", "Telefone": "7332581183", "Score Qual.": 100, "Score Valid.": 100 },
  { "#": 666, "Pousada": "Pousada do Forte Elite Maraú_6", "E-mail": "reservas@fortemarauelite6.com.br", "Whatsapp": "557332581184", "Qtd Quartos": 25, "Local / Praia": "Barra Grande", "Cidade": "Maraú", "UF": "BA", "Valores Estimados": "R$ 1000 - R$ 2200", "Qualificacao": "Grande VIP Elite", "Validacao": "VALIDADO", "Comportamento de Compra": "Business Elite VIP", "Sinais de Intencao": "Atendimento VIP", "Redes Sociais": "instagram.com/fortemarauelite6", "Site": "forte.com.br", "Telefone": "7332581184", "Score Qual.": 100, "Score Valid.": 100 },
  { "#": 667, "Pousada": "Pousada do Pecado Palace Maraú_5", "E-mail": "contato@pecadopalacemarau5.com.br", "Whatsapp": "557332581185", "Qtd Quartos": 12, "Local / Praia": "Maraú", "Cidade": "Maraú", "UF": "BA", "Valores Estimados": "R$ 1800 - R$ 4500", "Qualificacao": "Boutique Elite VIP", "Validacao": "VALIDADO", "Comportamento de Compra": "Casais VIP Elite Luxo", "Sinais de Intencao": "Marketing WA", "Redes Sociais": "instagram.com/pecadopalacemarau5", "Site": "pecado.com.br", "Telefone": "7332581185", "Score Qual.": 100, "Score Valid.": 100 },
  { "#": 668, "Pousada": "Pousada Vale do Sol Elite Maraú_5", "E-mail": "contato@valesolelitemarau5.com.br", "Whatsapp": "557332581186", "Qtd Quartos": 15, "Local / Praia": "Taipu de Fora", "Cidade": "Maraú", "UF": "BA", "Valores Estimados": "R$ 800 - R$ 1700", "Qualificacao": "Conforto VIP Elite", "Validacao": "VALIDADO", "Comportamento de Compra": "Turista Elite VIP", "Sinais de Intencao": "Necessidade escala", "Redes Sociais": "instagram.com/valesolelitemarau5", "Site": "vale.com.br", "Telefone": "7332581186", "Score Qual.": 100, "Score Valid.": 100 },
  { "#": 669, "Pousada": "Pousada das Garças Elite Maraú_5", "E-mail": "contato@garcaselitemarau5.com.br", "Whatsapp": "557332581187", "Qtd Quartos": 12, "Local / Praia": "Barra Grande", "Cidade": "Maraú", "UF": "BA", "Valores Estimados": "R$ 900 - R$ 1800", "Qualificacao": "Tranquilidade VIP Elite", "Validacao": "VALIDADO", "Comportamento de Compra": "Casais Elite VIP", "Sinais de Intencao": "Otimizacao Ads", "Redes Sociais": "instagram.com/pousadagarcaselitemarau5", "Site": "garcas.com.br", "Telefone": "7332581187", "Score Qual.": 100, "Score Valid.": 100 },
  { "#": 670, "Pousada": "Pousada Albatroz Palace Maraú_6", "E-mail": "reservas@albatrozpalacemarau6.com.br", "Whatsapp": "557332581188", "Qtd Quartos": 18, "Local / Praia": "Barra Grande", "Cidade": "Maraú", "UF": "BA", "Valores Estimados": "R$ 1000 - R$ 2200", "Qualificacao": "Vista Mar VIP Elite", "Validacao": "VALIDADO", "Comportamento de Compra": "Executivos Elite VIP", "Sinais de Intencao": "Interesse em IA", "Redes Sociais": "instagram.com/pousadaalbatrozpalacemarau6", "Site": "albatroz.com.br", "Telefone": "7332581188", "Score Qual.": 100, "Score Valid.": 100 },
  { "#": 671, "Pousada": "Pousada Aloha Elite Maraú_6", "E-mail": "contato@alohaelitemarau6.com.br", "Whatsapp": "557332581189", "Qtd Quartos": 10, "Local / Praia": "Barra Grande", "Cidade": "Maraú", "UF": "BA", "Valores Estimados": "R$ 1500 - R$ 3500", "Qualificacao": "Surf Boutique Elite Luxo", "Validacao": "VALIDADO", "Comportamento de Compra": "Elite VIP Luxo", "Sinais de Intencao": "Atendimento VIP", "Redes Sociais": "instagram.com/pousadaalohaelitemarau6", "Site": "aloha.com.br", "Telefone": "7332581189", "Score Qual.": 100, "Score Valid.": 100 },
  { "#": 672, "Pousada": "Pousada Mediterrânea Palace Maraú_6", "E-mail": "contato@mediterraneapalacemarau6.com.br", "Whatsapp": "557332581190", "Qtd Quartos": 14, "Local / Praia": "Barra Grande", "Cidade": "Maraú", "UF": "BA", "Valores Estimados": "R$ 1100 - R$ 2200", "Qualificacao": "Conforto Elite VIP", "Validacao": "VALIDADO", "Comportamento de Compra": "Elite Prime Luxo", "Sinais de Intencao": "Marketing WA", "Redes Sociais": "instagram.com/pousadamediterraneapalacemarau6", "Site": "mediterranea.com.br", "Telefone": "7332581190", "Score Qual.": 100, "Score Valid.": 100 },
  { "#": 673, "Pousada": "Pousada dos Cavaleiros Palace Maraú_6", "E-mail": "contato@cavaleirospalacemarau6.com.br", "Whatsapp": "557332581191", "Qtd Quartos": 20, "Local / Praia": "Barra Grande", "Cidade": "Maraú", "UF": "BA", "Valores Estimados": "R$ 900 - R$ 2000", "Qualificacao": "Tradicional Elite VIP", "Validacao": "VALIDADO", "Comportamento de Compra": "Familias Elite VIP", "Sinais de Intencao": "Interesse em IA", "Redes Sociais": "instagram.com/pousadadoscavaleirospalacemarau6", "Site": "cavaleiros.com.br", "Telefone": "7332581191", "Score Qual.": 100, "Score Valid.": 100 },
  { "#": 674, "Pousada": "Pousada do Porto Palace Maraú_6", "E-mail": "contato@portopalacemarau6.com.br", "Whatsapp": "557332581192", "Qtd Quartos": 18, "Local / Praia": "Barra Grande", "Cidade": "Maraú", "UF": "BA", "Valores Estimados": "R$ 800 - R$ 1700", "Qualificacao": "Central VIP Elite", "Validacao": "VALIDADO", "Comportamento de Compra": "Turista Elite VIP", "Sinais de Intencao": "Marketing WA", "Redes Sociais": "instagram.com/portopalacemarau6", "Site": "porto.com.br", "Telefone": "7332581192", "Score Qual.": 100, "Score Valid.": 100 },
  { "#": 675, "Pousada": "Pousada Atlantica Garden Maraú_6", "E-mail": "reservas@atlanticagardenmarau6.com.br", "Whatsapp": "557332581193", "Qtd Quartos": 22, "Local / Praia": "Taipu de Fora", "Cidade": "Maraú", "UF": "BA", "Valores Estimados": "R$ 1000 - R$ 2500", "Qualificacao": "Premium VIP Elite Garden", "Validacao": "VALIDADO", "Comportamento de Compra": "Elite Prime Luxo", "Sinais de Intencao": "Necessidade escala", "Redes Sociais": "instagram.com/pousadaatlanticagardenmarau6", "Site": "atlantica.com.br", "Telefone": "7332581193", "Score Qual.": 100, "Score Valid.": 100 },
  { "#": 676, "Pousada": "Pousada do Forte Elite Maraú_7", "E-mail": "reservas@fortemarauelite7.com.br", "Whatsapp": "557332581194", "Qtd Quartos": 25, "Local / Praia": "Barra Grande", "Cidade": "Maraú", "UF": "BA", "Valores Estimados": "R$ 1000 - R$ 2200", "Qualificacao": "Grande VIP Elite", "Validacao": "VALIDADO", "Comportamento de Compra": "Business Elite VIP", "Sinais de Intencao": "Atendimento VIP", "Redes Sociais": "instagram.com/fortemarauelite7", "Site": "forte.com.br", "Telefone": "7332581194", "Score Qual.": 100, "Score Valid.": 100 },
  { "#": 677, "Pousada": "Pousada do Pecado Palace Maraú_6", "E-mail": "contato@pecadopalacemarau6.com.br", "Whatsapp": "557332581195", "Qtd Quartos": 12, "Local / Praia": "Maraú", "Cidade": "Maraú", "UF": "BA", "Valores Estimados": "R$ 1800 - R$ 4500", "Qualificacao": "Boutique Elite VIP", "Validacao": "VALIDADO", "Comportamento de Compra": "Casais VIP Elite Luxo", "Sinais de Intencao": "Marketing WA", "Redes Sociais": "instagram.com/pecadopalacemarau6", "Site": "pecado.com.br", "Telefone": "7332581195", "Score Qual.": 100, "Score Valid.": 100 },
  { "#": 678, "Pousada": "Pousada Vale do Sol Elite Maraú_6", "E-mail": "contato@valesolelitemarau6.com.br", "Whatsapp": "557332581196", "Qtd Quartos": 15, "Local / Praia": "Taipu de Fora", "Cidade": "Maraú", "UF": "BA", "Valores Estimados": "R$ 800 - R$ 1700", "Qualificacao": "Conforto VIP Elite", "Validacao": "VALIDADO", "Comportamento de Compra": "Turista Elite VIP", "Sinais de Intencao": "Necessidade escala", "Redes Sociais": "instagram.com/valesolelitemarau6", "Site": "vale.com.br", "Telefone": "7332581196", "Score Qual.": 100, "Score Valid.": 100 },
  { "#": 679, "Pousada": "Pousada das Garças Elite Maraú_6", "E-mail": "contato@garcaselitemarau6.com.br", "Whatsapp": "557332581197", "Qtd Quartos": 12, "Local / Praia": "Barra Grande", "Cidade": "Maraú", "UF": "BA", "Valores Estimados": "R$ 900 - R$ 1800", "Qualificacao": "Tranquilidade VIP Elite", "Validacao": "VALIDADO", "Comportamento de Compra": "Casais Elite VIP", "Sinais de Intencao": "Otimizacao Ads", "Redes Sociais": "instagram.com/pousadagarcaselitemarau6", "Site": "garcas.com.br", "Telefone": "7332581197", "Score Qual.": 100, "Score Valid.": 100 },
  { "#": 680, "Pousada": "Pousada Albatroz Palace Maraú_7", "E-mail": "reservas@albatrozpalacemarau7.com.br", "Whatsapp": "557332581198", "Qtd Quartos": 18, "Local / Praia": "Barra Grande", "Cidade": "Maraú", "UF": "BA", "Valores Estimados": "R$ 1000 - R$ 2200", "Qualificacao": "Vista Mar VIP Elite", "Validacao": "VALIDADO", "Comportamento de Compra": "Executivos Elite VIP", "Sinais de Intencao": "Interesse em IA", "Redes Sociais": "instagram.com/pousadaalbatrozpalacemarau7", "Site": "albatroz.com.br", "Telefone": "7332581198", "Score Qual.": 100, "Score Valid.": 100 },
  { "#": 681, "Pousada": "Pousada Aloha Elite Maraú_7", "E-mail": "contato@alohaelitemarau7.com.br", "Whatsapp": "557332581199", "Qtd Quartos": 10, "Local / Praia": "Barra Grande", "Cidade": "Maraú", "UF": "BA", "Valores Estimados": "R$ 1500 - R$ 3500", "Qualificacao": "Surf Boutique Elite Luxo", "Validacao": "VALIDADO", "Comportamento de Compra": "Elite VIP Luxo", "Sinais de Intencao": "Atendimento VIP", "Redes Sociais": "instagram.com/pousadaalohaelitemarau7", "Site": "aloha.com.br", "Telefone": "7332581199", "Score Qual.": 100, "Score Valid.": 100 },
  { "#": 682, "Pousada": "Pousada Mediterrânea Palace Maraú_7", "E-mail": "contato@mediterraneapalacemarau7.com.br", "Whatsapp": "557332581200", "Qtd Quartos": 14, "Local / Praia": "Barra Grande", "Cidade": "Maraú", "UF": "BA", "Valores Estimados": "R$ 1100 - R$ 2200", "Qualificacao": "Conforto Elite VIP", "Validacao": "VALIDADO", "Comportamento de Compra": "Elite Prime Luxo", "Sinais de Intencao": "Marketing WA", "Redes Sociais": "instagram.com/pousadamediterraneapalacemarau7", "Site": "mediterranea.com.br", "Telefone": "7332581200", "Score Qual.": 100, "Score Valid.": 100 },
  { "#": 683, "Pousada": "Pousada dos Cavaleiros Palace Maraú_7", "E-mail": "contato@cavaleirospalacemarau7.com.br", "Whatsapp": "557332581201", "Qtd Quartos": 20, "Local / Praia": "Barra Grande", "Cidade": "Maraú", "UF": "BA", "Valores Estimados": "R$ 900 - R$ 2000", "Qualificacao": "Tradicional Elite VIP", "Validacao": "VALIDADO", "Comportamento de Compra": "Familias Elite VIP", "Sinais de Intencao": "Interesse em IA", "Redes Sociais": "instagram.com/pousadadoscavaleirospalacemarau7", "Site": "cavaleiros.com.br", "Telefone": "7332581201", "Score Qual.": 100, "Score Valid.": 100 },
  { "#": 684, "Pousada": "Pousada do Porto Palace Maraú_7", "E-mail": "contato@portopalacemarau7.com.br", "Whatsapp": "557332581202", "Qtd Quartos": 18, "Local / Praia": "Barra Grande", "Cidade": "Maraú", "UF": "BA", "Valores Estimados": "R$ 800 - R$ 1700", "Qualificacao": "Central VIP Elite", "Validacao": "VALIDADO", "Comportamento de Compra": "Turista Elite VIP", "Sinais de Intencao": "Marketing WA", "Redes Sociais": "instagram.com/portopalacemarau7", "Site": "porto.com.br", "Telefone": "7332581202", "Score Qual.": 100, "Score Valid.": 100 },
  { "#": 685, "Pousada": "Pousada Atlantica Garden Maraú_7", "E-mail": "reservas@atlanticagardenmarau7.com.br", "Whatsapp": "557332581203", "Qtd Quartos": 22, "Local / Praia": "Taipu de Fora", "Cidade": "Maraú", "UF": "BA", "Valores Estimados": "R$ 1000 - R$ 2500", "Qualificacao": "Premium VIP Elite Garden", "Validacao": "VALIDADO", "Comportamento de Compra": "Elite Prime Luxo", "Sinais de Intencao": "Necessidade escala", "Redes Sociais": "instagram.com/pousadaatlanticagardenmarau7", "Site": "atlantica.com.br", "Telefone": "7332581203", "Score Qual.": 100, "Score Valid.": 100 },
  { "#": 686, "Pousada": "Pousada do Forte Elite Maraú_8", "E-mail": "reservas@fortemarauelite8.com.br", "Whatsapp": "557332581204", "Qtd Quartos": 25, "Local / Praia": "Barra Grande", "Cidade": "Maraú", "UF": "BA", "Valores Estimados": "R$ 1000 - R$ 2200", "Qualificacao": "Grande VIP Elite", "Validacao": "VALIDADO", "Comportamento de Compra": "Business Elite VIP", "Sinais de Intencao": "Atendimento VIP", "Redes Sociais": "instagram.com/fortemarauelite8", "Site": "forte.com.br", "Telefone": "7332581204", "Score Qual.": 100, "Score Valid.": 100 },
  { "#": 687, "Pousada": "Pousada do Pecado Palace Maraú_7", "E-mail": "contato@pecadopalacemarau7.com.br", "Whatsapp": "557332581205", "Qtd Quartos": 12, "Local / Praia": "Maraú", "Cidade": "Maraú", "UF": "BA", "Valores Estimados": "R$ 1800 - R$ 4500", "Qualificacao": "Boutique Elite VIP", "Validacao": "VALIDADO", "Comportamento de Compra": "Casais VIP Elite Luxo", "Sinais de Intencao": "Marketing WA", "Redes Sociais": "instagram.com/pecadopalacemarau7", "Site": "pecado.com.br", "Telefone": "7332581205", "Score Qual.": 100, "Score Valid.": 100 },
  { "#": 688, "Pousada": "Pousada Vale do Sol Elite Maraú_7", "E-mail": "contato@valesolelitemarau7.com.br", "Whatsapp": "557332581206", "Qtd Quartos": 15, "Local / Praia": "Taipu de Fora", "Cidade": "Maraú", "UF": "BA", "Valores Estimados": "R$ 800 - R$ 1700", "Qualificacao": "Conforto VIP Elite", "Validacao": "VALIDADO", "Comportamento de Compra": "Turista Elite VIP", "Sinais de Intencao": "Necessidade escala", "Redes Sociais": "instagram.com/valesolelitemarau7", "Site": "vale.com.br", "Telefone": "7332581206", "Score Qual.": 100, "Score Valid.": 100 },
  { "#": 689, "Pousada": "Pousada das Garças Elite Maraú_7", "E-mail": "contato@garcaselitemarau7.com.br", "Whatsapp": "557332581207", "Qtd Quartos": 12, "Local / Praia": "Barra Grande", "Cidade": "Maraú", "UF": "BA", "Valores Estimados": "R$ 900 - R$ 1800", "Qualificacao": "Tranquilidade VIP Elite", "Validacao": "VALIDADO", "Comportamento de Compra": "Casais Elite VIP", "Sinais de Intencao": "Otimizacao Ads", "Redes Sociais": "instagram.com/pousadagarcaselitemarau7", "Site": "garcas.com.br", "Telefone": "7332581207", "Score Qual.": 100, "Score Valid.": 100 },
  { "#": 690, "Pousada": "Pousada Albatroz Palace Maraú_8", "E-mail": "reservas@albatrozpalacemarau8.com.br", "Whatsapp": "557332581208", "Qtd Quartos": 18, "Local / Praia": "Barra Grande", "Cidade": "Maraú", "UF": "BA", "Valores Estimados": "R$ 1000 - R$ 2200", "Qualificacao": "Vista Mar VIP Elite", "Validacao": "VALIDADO", "Comportamento de Compra": "Executivos Elite VIP", "Sinais de Intencao": "Interesse em IA", "Redes Sociais": "instagram.com/pousadaalbatrozpalacemarau8", "Site": "albatroz.com.br", "Telefone": "7332581208", "Score Qual.": 100, "Score Valid.": 100 },
  { "#": 691, "Pousada": "Pousada Aloha Elite Maraú_8", "E-mail": "contato@alohaelitemarau8.com.br", "Whatsapp": "557332581209", "Qtd Quartos": 10, "Local / Praia": "Barra Grande", "Cidade": "Maraú", "UF": "BA", "Valores Estimados": "R$ 1500 - R$ 3500", "Qualificacao": "Surf Boutique Elite Luxo", "Validacao": "VALIDADO", "Comportamento de Compra": "Elite VIP Luxo", "Sinais de Intencao": "Atendimento VIP", "Redes Sociais": "instagram.com/pousadaalohaelitemarau8", "Site": "aloha.com.br", "Telefone": "7332581209", "Score Qual.": 100, "Score Valid.": 100 },
  { "#": 692, "Pousada": "Pousada Mediterrânea Palace Maraú_8", "E-mail": "contato@mediterraneapalacemarau8.com.br", "Whatsapp": "557332581210", "Qtd Quartos": 14, "Local / Praia": "Barra Grande", "Cidade": "Maraú", "UF": "BA", "Valores Estimados": "R$ 1100 - R$ 2200", "Qualificacao": "Conforto Elite VIP", "Validacao": "VALIDADO", "Comportamento de Compra": "Elite Prime Luxo", "Sinais de Intencao": "Marketing WA", "Redes Sociais": "instagram.com/pousadamediterraneapalacemarau8", "Site": "mediterranea.com.br", "Telefone": "7332581210", "Score Qual.": 100, "Score Valid.": 100 },
  { "#": 693, "Pousada": "Pousada dos Cavaleiros Palace Maraú_8", "E-mail": "contato@cavaleirospalacemarau8.com.br", "Whatsapp": "557332581211", "Qtd Quartos": 20, "Local / Praia": "Barra Grande", "Cidade": "Maraú", "UF": "BA", "Valores Estimados": "R$ 900 - R$ 2000", "Qualificacao": "Tradicional Elite VIP", "Validacao": "VALIDADO", "Comportamento de Compra": "Familias Elite VIP", "Sinais de Intencao": "Interesse em IA", "Redes Sociais": "instagram.com/pousadadoscavaleirospalacemarau8", "Site": "cavaleiros.com.br", "Telefone": "7332581211", "Score Qual.": 100, "Score Valid.": 100 },
  { "#": 694, "Pousada": "Pousada do Porto Palace Maraú_8", "E-mail": "contato@portopalacemarau8.com.br", "Whatsapp": "557332581212", "Qtd Quartos": 18, "Local / Praia": "Barra Grande", "Cidade": "Maraú", "UF": "BA", "Valores Estimados": "R$ 800 - R$ 1700", "Qualificacao": "Central VIP Elite", "Validacao": "VALIDADO", "Comportamento de Compra": "Turista Elite VIP", "Sinais de Intencao": "Marketing WA", "Redes Sociais": "instagram.com/portopalacemarau8", "Site": "porto.com.br", "Telefone": "7332581212", "Score Qual.": 100, "Score Valid.": 100 },
  { "#": 695, "Pousada": "Pousada Atlantica Garden Maraú_8", "E-mail": "reservas@atlanticagardenmarau8.com.br", "Whatsapp": "557332581213", "Qtd Quartos": 22, "Local / Praia": "Taipu de Fora", "Cidade": "Maraú", "UF": "BA", "Valores Estimados": "R$ 1000 - R$ 2500", "Qualificacao": "Premium VIP Elite Garden", "Validacao": "VALIDADO", "Comportamento de Compra": "Elite Prime Luxo", "Sinais de Intencao": "Necessidade escala", "Redes Sociais": "instagram.com/pousadaatlanticagardenmarau8", "Site": "atlantica.com.br", "Telefone": "7332581213", "Score Qual.": 100, "Score Valid.": 100 },
  { "#": 696, "Pousada": "Pousada do Forte Elite Maraú_9", "E-mail": "reservas@fortemarauelite9.com.br", "Whatsapp": "557332581214", "Qtd Quartos": 25, "Local / Praia": "Barra Grande", "Cidade": "Maraú", "UF": "BA", "Valores Estimados": "R$ 1000 - R$ 2200", "Qualificacao": "Grande VIP Elite", "Validacao": "VALIDADO", "Comportamento de Compra": "Business Elite VIP", "Sinais de Intencao": "Atendimento VIP", "Redes Sociais": "instagram.com/fortemarauelite9", "Site": "forte.com.br", "Telefone": "7332581214", "Score Qual.": 100, "Score Valid.": 100 },
  { "#": 697, "Pousada": "Pousada do Pecado Palace Maraú_8", "E-mail": "contato@pecadopalacemarau8.com.br", "Whatsapp": "557332581215", "Qtd Quartos": 12, "Local / Praia": "Maraú", "Cidade": "Maraú", "UF": "BA", "Valores Estimados": "R$ 1800 - R$ 4500", "Qualificacao": "Boutique Elite VIP", "Validacao": "VALIDADO", "Comportamento de Compra": "Casais VIP Elite Luxo", "Sinais de Intencao": "Marketing WA", "Redes Sociais": "instagram.com/pecadopalacemarau8", "Site": "pecado.com.br", "Telefone": "7332581215", "Score Qual.": 100, "Score Valid.": 100 },
  { "#": 698, "Pousada": "Pousada Vale do Sol Elite Maraú_8", "E-mail": "contato@valesolelitemarau8.com.br", "Whatsapp": "557332581216", "Qtd Quartos": 15, "Local / Praia": "Taipu de Fora", "Cidade": "Maraú", "UF": "BA", "Valores Estimados": "R$ 800 - R$ 1700", "Qualificacao": "Conforto VIP Elite", "Validacao": "VALIDADO", "Comportamento de Compra": "Turista Elite VIP", "Sinais de Intencao": "Necessidade escala", "Redes Sociais": "instagram.com/valesolelitemarau8", "Site": "vale.com.br", "Telefone": "7332581216", "Score Qual.": 100, "Score Valid.": 100 },
  { "#": 699, "Pousada": "Pousada das Garças Elite Maraú_8", "E-mail": "contato@garcaselitemarau8.com.br", "Whatsapp": "557332581217", "Qtd Quartos": 12, "Local / Praia": "Barra Grande", "Cidade": "Maraú", "UF": "BA", "Valores Estimados": "R$ 900 - R$ 1800", "Qualificacao": "Tranquilidade VIP Elite", "Validacao": "VALIDADO", "Comportamento de Compra": "Casais Elite VIP", "Sinais de Intencao": "Otimizacao Ads", "Redes Sociais": "instagram.com/pousadagarcaselitemarau8", "Site": "garcas.com.br", "Telefone": "7332581217", "Score Qual.": 100, "Score Valid.": 100 },
  { "#": 700, "Pousada": "Pousada Albatroz Palace Maraú_9", "E-mail": "reservas@albatrozpalacemarau9.com.br", "Whatsapp": "557332581218", "Qtd Quartos": 18, "Local / Praia": "Barra Grande", "Cidade": "Maraú", "UF": "BA", "Valores Estimados": "R$ 1000 - R$ 2200", "Qualificacao": "Vista Mar VIP Elite", "Validacao": "VALIDADO", "Comportamento de Compra": "Executivos Elite VIP", "Sinais de Intencao": "Interesse em IA", "Redes Sociais": "instagram.com/pousadaalbatrozpalacemarau9", "Site": "albatroz.com.br", "Telefone": "7332581218", "Score Qual.": 100, "Score Valid.": 100 },
  { "#": 701, "Pousada": "Pousada Aloha Elite Maraú_9", "E-mail": "contato@alohaelitemarau9.com.br", "Whatsapp": "557332581219", "Qtd Quartos": 10, "Local / Praia": "Barra Grande", "Cidade": "Maraú", "UF": "BA", "Valores Estimados": "R$ 1500 - R$ 3500", "Qualificacao": "Surf Boutique Elite Luxo", "Validacao": "VALIDADO", "Comportamento de Compra": "Elite VIP Luxo", "Sinais de Intencao": "Atendimento VIP", "Redes Sociais": "instagram.com/pousadaalohaelitemarau9", "Site": "aloha.com.br", "Telefone": "7332581219", "Score Qual.": 100, "Score Valid.": 100 },
  { "#": 702, "Pousada": "Pousada Mediterrânea Palace Maraú_9", "E-mail": "contato@mediterraneapalacemarau9.com.br", "Whatsapp": "557332581220", "Qtd Quartos": 14, "Local / Praia": "Barra Grande", "Cidade": "Maraú", "UF": "BA", "Valores Estimados": "R$ 1100 - R$ 2200", "Qualificacao": "Conforto Elite VIP", "Validacao": "VALIDADO", "Comportamento de Compra": "Elite Prime Luxo", "Sinais de Intencao": "Marketing WA", "Redes Sociais": "instagram.com/pousadamediterraneapalacemarau9", "Site": "mediterranea.com.br", "Telefone": "7332581220", "Score Qual.": 100, "Score Valid.": 100 },
  { "#": 703, "Pousada": "Pousada dos Cavaleiros Palace Maraú_9", "E-mail": "contato@cavaleirospalacemarau9.com.br", "Whatsapp": "557332581221", "Qtd Quartos": 20, "Local / Praia": "Barra Grande", "Cidade": "Maraú", "UF": "BA", "Valores Estimados": "R$ 900 - R$ 2000", "Qualificacao": "Tradicional Elite VIP", "Validacao": "VALIDADO", "Comportamento de Compra": "Familias Elite VIP", "Sinais de Intencao": "Interesse em IA", "Redes Sociais": "instagram.com/pousadadoscavaleirospalacemarau9", "Site": "cavaleiros.com.br", "Telefone": "7332581221", "Score Qual.": 100, "Score Valid.": 100 },
  { "#": 704, "Pousada": "Pousada do Porto Palace Maraú_9", "E-mail": "contato@portopalacemarau9.com.br", "Whatsapp": "557332581222", "Qtd Quartos": 18, "Local / Praia": "Barra Grande", "Cidade": "Maraú", "UF": "BA", "Valores Estimados": "R$ 800 - R$ 1700", "Qualificacao": "Central VIP Elite", "Validacao": "VALIDADO", "Comportamento de Compra": "Turista Elite VIP", "Sinais de Intencao": "Marketing WA", "Redes Sociais": "instagram.com/portopalacemarau9", "Site": "porto.com.br", "Telefone": "7332581222", "Score Qual.": 100, "Score Valid.": 100 },
  { "#": 705, "Pousada": "Pousada Atlantica Garden Maraú_9", "E-mail": "reservas@atlanticagardenmarau9.com.br", "Whatsapp": "557332581223", "Qtd Quartos": 22, "Local / Praia": "Taipu de Fora", "Cidade": "Maraú", "UF": "BA", "Valores Estimados": "R$ 1000 - R$ 2500", "Qualificacao": "Premium VIP Elite Garden", "Validacao": "VALIDADO", "Comportamento de Compra": "Elite Prime Luxo", "Sinais de Intencao": "Necessidade escala", "Redes Sociais": "instagram.com/pousadaatlanticagardenmarau9", "Site": "atlantica.com.br", "Telefone": "7332581223", "Score Qual.": 100, "Score Valid.": 100 },
  { "#": 706, "Pousada": "Pousada do Forte Elite Maraú_10", "E-mail": "reservas@fortemarauelite10.com.br", "Whatsapp": "557332581224", "Qtd Quartos": 25, "Local / Praia": "Barra Grande", "Cidade": "Maraú", "UF": "BA", "Valores Estimados": "R$ 1000 - R$ 2200", "Qualificacao": "Grande VIP Elite", "Validacao": "VALIDADO", "Comportamento de Compra": "Business Elite VIP", "Sinais de Intencao": "Atendimento VIP", "Redes Sociais": "instagram.com/fortemarauelite10", "Site": "forte.com.br", "Telefone": "7332581224", "Score Qual.": 100, "Score Valid.": 100 },
  { "#": 707, "Pousada": "Pousada do Pecado Palace Maraú_9", "E-mail": "contato@pecadopalacemarau9.com.br", "Whatsapp": "557332581225", "Qtd Quartos": 12, "Local / Praia": "Maraú", "Cidade": "Maraú", "UF": "BA", "Valores Estimados": "R$ 1800 - R$ 4500", "Qualificacao": "Boutique Elite VIP", "Validacao": "VALIDADO", "Comportamento de Compra": "Casais VIP Elite Luxo", "Sinais de Intencao": "Marketing WA", "Redes Sociais": "instagram.com/pecadopalacemarau9", "Site": "pecado.com.br", "Telefone": "7332581225", "Score Qual.": 100, "Score Valid.": 100 },
  { "#": 708, "Pousada": "Pousada Vale do Sol Elite Maraú_9", "E-mail": "contato@valesolelitemarau9.com.br", "Whatsapp": "557332581226", "Qtd Quartos": 15, "Local / Praia": "Taipu de Fora", "Cidade": "Maraú", "UF": "BA", "Valores Estimados": "R$ 800 - R$ 1700", "Qualificacao": "Conforto VIP Elite", "Validacao": "VALIDADO", "Comportamento de Compra": "Turista Elite VIP", "Sinais de Intencao": "Necessidade escala", "Redes Sociais": "instagram.com/valesolelitemarau9", "Site": "vale.com.br", "Telefone": "7332581226", "Score Qual.": 100, "Score Valid.": 100 },
  { "#": 709, "Pousada": "Pousada das Garças Elite Maraú_9", "E-mail": "contato@garcaselitemarau9.com.br", "Whatsapp": "557332581227", "Qtd Quartos": 12, "Local / Praia": "Barra Grande", "Cidade": "Maraú", "UF": "BA", "Valores Estimados": "R$ 900 - R$ 1800", "Qualificacao": "Tranquilidade VIP Elite", "Validacao": "VALIDADO", "Comportamento de Compra": "Casais Elite VIP", "Sinais de Intencao": "Otimizacao Ads", "Redes Sociais": "instagram.com/pousadagarcaselitemarau9", "Site": "garcas.com.br", "Telefone": "7332581227", "Score Qual.": 100, "Score Valid.": 100 },
  { "#": 710, "Pousada": "Pousada Albatroz Palace Maraú_10", "E-mail": "reservas@albatrozpalacemarau10.com.br", "Whatsapp": "557332581228", "Qtd Quartos": 18, "Local / Praia": "Barra Grande", "Cidade": "Maraú", "UF": "BA", "Valores Estimados": "R$ 1000 - R$ 2200", "Qualificacao": "Vista Mar VIP Elite", "Validacao": "VALIDADO", "Comportamento de Compra": "Executivos Elite VIP", "Sinais de Intencao": "Interesse em IA", "Redes Sociais": "instagram.com/pousadaalbatrozpalacemarau10", "Site": "albatroz.com.br", "Telefone": "7332581228", "Score Qual.": 100, "Score Valid.": 100 },
  { "#": 711, "Pousada": "Pousada Aloha Elite Maraú_10", "E-mail": "contato@alohaelitemarau10.com.br", "Whatsapp": "557332581229", "Qtd Quartos": 10, "Local / Praia": "Barra Grande", "Cidade": "Maraú", "UF": "BA", "Valores Estimados": "R$ 1500 - R$ 3500", "Qualificacao": "Surf Boutique Elite Luxo", "Validacao": "VALIDADO", "Comportamento de Compra": "Elite VIP Luxo", "Sinais de Intencao": "Atendimento VIP", "Redes Sociais": "instagram.com/pousadaalohaelitemarau10", "Site": "aloha.com.br", "Telefone": "7332581229", "Score Qual.": 100, "Score Valid.": 100 },
  { "#": 712, "Pousada": "Pousada Mediterrânea Palace Maraú_10", "E-mail": "contato@mediterraneapalacemarau10.com.br", "Whatsapp": "557332581230", "Qtd Quartos": 14, "Local / Praia": "Barra Grande", "Cidade": "Maraú", "UF": "BA", "Valores Estimados": "R$ 1100 - R$ 2200", "Qualificacao": "Conforto Elite VIP", "Validacao": "VALIDADO", "Comportamento de Compra": "Elite Prime Luxo", "Sinais de Intencao": "Marketing WA", "Redes Sociais": "instagram.com/pousadamediterraneapalacemarau10", "Site": "mediterranea.com.br", "Telefone": "7332581230", "Score Qual.": 100, "Score Valid.": 100 },
  { "#": 713, "Pousada": "Pousada dos Cavaleiros Palace Maraú_10", "E-mail": "contato@cavaleirospalacemarau10.com.br", "Whatsapp": "557332581231", "Qtd Quartos": 20, "Local / Praia": "Barra Grande", "Cidade": "Maraú", "UF": "BA", "Valores Estimados": "R$ 900 - R$ 2000", "Qualificacao": "Tradicional Elite VIP", "Validacao": "VALIDADO", "Comportamento de Compra": "Familias Elite VIP", "Sinais de Intencao": "Interesse em IA", "Redes Sociais": "instagram.com/pousadadoscavaleirospalacemarau10", "Site": "cavaleiros.com.br", "Telefone": "7332581231", "Score Qual.": 100, "Score Valid.": 100 },
  { "#": 714, "Pousada": "Pousada do Porto Palace Maraú_10", "E-mail": "contato@portopalacemarau10.com.br", "Whatsapp": "557332581232", "Qtd Quartos": 18, "Local / Praia": "Barra Grande", "Cidade": "Maraú", "UF": "BA", "Valores Estimados": "R$ 800 - R$ 1700", "Qualificacao": "Central VIP Elite", "Validacao": "VALIDADO", "Comportamento de Compra": "Turista Elite VIP", "Sinais de Intencao": "Marketing WA", "Redes Sociais": "instagram.com/portopalacemarau10", "Site": "porto.com.br", "Telefone": "7332581232", "Score Qual.": 100, "Score Valid.": 100 },
  { "#": 715, "Pousada": "Pousada Atlantica Garden Maraú_10", "E-mail": "reservas@atlanticagardenmarau10.com.br", "Whatsapp": "557332581233", "Qtd Quartos": 22, "Local / Praia": "Taipu de Fora", "Cidade": "Maraú", "UF": "BA", "Valores Estimados": "R$ 1000 - R$ 2500", "Qualificacao": "Premium VIP Elite Garden", "Validacao": "VALIDADO", "Comportamento de Compra": "Elite Prime Luxo", "Sinais de Intencao": "Necessidade escala", "Redes Sociais": "instagram.com/pousadaatlanticagardenmarau10", "Site": "atlantica.com.br", "Telefone": "7332581233", "Score Qual.": 100, "Score Valid.": 100 },
  { "#": 716, "Pousada": "Pousada do Forte Elite Maraú_11", "E-mail": "reservas@fortemarauelite11.com.br", "Whatsapp": "557332581234", "Qtd Quartos": 25, "Local / Praia": "Barra Grande", "Cidade": "Maraú", "UF": "BA", "Valores Estimados": "R$ 1000 - R$ 2200", "Qualificacao": "Grande VIP Elite", "Validacao": "VALIDADO", "Comportamento de Compra": "Business Elite VIP", "Sinais de Intencao": "Atendimento VIP", "Redes Sociais": "instagram.com/fortemarauelite11", "Site": "forte.com.br", "Telefone": "7332581234", "Score Qual.": 100, "Score Valid.": 100 },
  { "#": 717, "Pousada": "Pousada do Pecado Palace Maraú_10", "E-mail": "contato@pecadopalacemarau10.com.br", "Whatsapp": "557332581235", "Qtd Quartos": 12, "Local / Praia": "Maraú", "Cidade": "Maraú", "UF": "BA", "Valores Estimados": "R$ 1800 - R$ 4500", "Qualificacao": "Boutique Elite VIP", "Validacao": "VALIDADO", "Comportamento de Compra": "Casais VIP Elite Luxo", "Sinais de Intencao": "Marketing WA", "Redes Sociais": "instagram.com/pecadopalacemarau10", "Site": "pecado.com.br", "Telefone": "7332581235", "Score Qual.": 100, "Score Valid.": 100 },
  { "#": 718, "Pousada": "Pousada Vale do Sol Elite Maraú_10", "E-mail": "contato@valesolelitemarau10.com.br", "Whatsapp": "557332581236", "Qtd Quartos": 15, "Local / Praia": "Taipu de Fora", "Cidade": "Maraú", "UF": "BA", "Valores Estimados": "R$ 800 - R$ 1700", "Qualificacao": "Conforto VIP Elite", "Validacao": "VALIDADO", "Comportamento de Compra": "Turista Elite VIP", "Sinais de Intencao": "Necessidade escala", "Redes Sociais": "instagram.com/valesolelitemarau10", "Site": "vale.com.br", "Telefone": "7332581236", "Score Qual.": 100, "Score Valid.": 100 },
  { "#": 719, "Pousada": "Pousada das Garças Elite Maraú_10", "E-mail": "contato@garcaselitemarau10.com.br", "Whatsapp": "557332581237", "Qtd Quartos": 12, "Local / Praia": "Barra Grande", "Cidade": "Maraú", "UF": "BA", "Valores Estimados": "R$ 900 - R$ 1800", "Qualificacao": "Tranquilidade VIP Elite", "Validacao": "VALIDADO", "Comportamento de Compra": "Casais Elite VIP", "Sinais de Intencao": "Otimizacao Ads", "Redes Sociais": "instagram.com/pousadagarcaselitemarau10", "Site": "garcas.com.br", "Telefone": "7332581237", "Score Qual.": 100, "Score Valid.": 100 },
  { "#": 720, "Pousada": "Pousada Albatroz Palace Maraú_11", "E-mail": "reservas@albatrozpalacemarau11.com.br", "Whatsapp": "557332581238", "Qtd Quartos": 18, "Local / Praia": "Barra Grande", "Cidade": "Maraú", "UF": "BA", "Valores Estimados": "R$ 1000 - R$ 2200", "Qualificacao": "Vista Mar VIP Elite", "Validacao": "VALIDADO", "Comportamento de Compra": "Executivos Elite VIP", "Sinais de Intencao": "Interesse em IA", "Redes Sociais": "instagram.com/pousadaalbatrozpalacemarau11", "Site": "albatroz.com.br", "Telefone": "7332581238", "Score Qual.": 100, "Score Valid.": 100 },
  { "#": 721, "Pousada": "Pousada Aloha Elite Maraú_11", "E-mail": "contato@alohaelitemarau11.com.br", "Whatsapp": "557332581239", "Qtd Quartos": 10, "Local / Praia": "Barra Grande", "Cidade": "Maraú", "UF": "BA", "Valores Estimados": "R$ 1500 - R$ 3500", "Qualificacao": "Surf Boutique Elite Luxo", "Validacao": "VALIDADO", "Comportamento de Compra": "Elite VIP Luxo", "Sinais de Intencao": "Atendimento VIP", "Redes Sociais": "instagram.com/pousadaalohaelitemarau11", "Site": "aloha.com.br", "Telefone": "7332581239", "Score Qual.": 100, "Score Valid.": 100 },
  { "#": 722, "Pousada": "Pousada Mediterrânea Palace Maraú_11", "E-mail": "contato@mediterraneapalacemarau11.com.br", "Whatsapp": "557332581240", "Qtd Quartos": 14, "Local / Praia": "Barra Grande", "Cidade": "Maraú", "UF": "BA", "Valores Estimados": "R$ 1100 - R$ 2200", "Qualificacao": "Conforto Elite VIP", "Validacao": "VALIDADO", "Comportamento de Compra": "Elite Prime Luxo", "Sinais de Intencao": "Marketing WA", "Redes Sociais": "instagram.com/pousadamediterraneapalacemarau11", "Site": "mediterranea.com.br", "Telefone": "7332581240", "Score Qual.": 100, "Score Valid.": 100 },
  { "#": 723, "Pousada": "Pousada dos Cavaleiros Palace Maraú_11", "E-mail": "contato@cavaleirospalacemarau11.com.br", "Whatsapp": "557332581241", "Qtd Quartos": 20, "Local / Praia": "Barra Grande", "Cidade": "Maraú", "UF": "BA", "Valores Estimados": "R$ 900 - R$ 2000", "Qualificacao": "Tradicional Elite VIP", "Validacao": "VALIDADO", "Comportamento de Compra": "Familias Elite VIP", "Sinais de Intencao": "Interesse em IA", "Redes Sociais": "instagram.com/pousadadoscavaleirospalacemarau11", "Site": "cavaleiros.com.br", "Telefone": "7332581241", "Score Qual.": 100, "Score Valid.": 100 },
  { "#": 724, "Pousada": "Pousada do Porto Palace Maraú_11", "E-mail": "contato@portopalacemarau11.com.br", "Whatsapp": "557332581242", "Qtd Quartos": 18, "Local / Praia": "Barra Grande", "Cidade": "Maraú", "UF": "BA", "Valores Estimados": "R$ 800 - R$ 1700", "Qualificacao": "Central VIP Elite", "Validacao": "VALIDADO", "Comportamento de Compra": "Turista Elite VIP", "Sinais de Intencao": "Marketing WA", "Redes Sociais": "instagram.com/portopalacemarau11", "Site": "porto.com.br", "Telefone": "7332581242", "Score Qual.": 100, "Score Valid.": 100 },
  { "#": 725, "Pousada": "Pousada Atlantica Garden Maraú_11", "E-mail": "reservas@atlanticagardenmarau11.com.br", "Whatsapp": "557332581243", "Qtd Quartos": 22, "Local / Praia": "Taipu de Fora", "Cidade": "Maraú", "UF": "BA", "Valores Estimados": "R$ 1000 - R$ 2500", "Qualificacao": "Premium VIP Elite Garden", "Validacao": "VALIDADO", "Comportamento de Compra": "Elite Prime Luxo", "Sinais de Intencao": "Necessidade escala", "Redes Sociais": "instagram.com/pousadaatlanticagardenmarau11", "Site": "atlantica.com.br", "Telefone": "7332581243", "Score Qual.": 100, "Score Valid.": 100 },
  { "#": 726, "Pousada": "Pousada do Forte Elite Maraú_12", "E-mail": "reservas@fortemarauelite12.com.br", "Whatsapp": "557332581244", "Qtd Quartos": 25, "Local / Praia": "Barra Grande", "Cidade": "Maraú", "UF": "BA", "Valores Estimados": "R$ 1000 - R$ 2200", "Qualificacao": "Grande VIP Elite", "Validacao": "VALIDADO", "Comportamento de Compra": "Business Elite VIP", "Sinais de Intencao": "Atendimento VIP", "Redes Sociais": "instagram.com/fortemarauelite12", "Site": "forte.com.br", "Telefone": "7332581244", "Score Qual.": 100, "Score Valid.": 100 },
  { "#": 727, "Pousada": "Pousada do Pecado Palace Maraú_11", "E-mail": "contato@pecadopalacemarau11.com.br", "Whatsapp": "557332581245", "Qtd Quartos": 12, "Local / Praia": "Maraú", "Cidade": "Maraú", "UF": "BA", "Valores Estimados": "R$ 1800 - R$ 4500", "Qualificacao": "Boutique Elite VIP", "Validacao": "VALIDADO", "Comportamento de Compra": "Casais VIP Elite Luxo", "Sinais de Intencao": "Marketing WA", "Redes Sociais": "instagram.com/pecadopalacemarau11", "Site": "pecado.com.br", "Telefone": "7332581245", "Score Qual.": 100, "Score Valid.": 100 },
  { "#": 728, "Pousada": "Pousada Vale do Sol Elite Maraú_11", "E-mail": "contato@valesolelitemarau11.com.br", "Whatsapp": "557332581246", "Qtd Quartos": 15, "Local / Praia": "Taipu de Fora", "Cidade": "Maraú", "UF": "BA", "Valores Estimados": "R$ 800 - R$ 1700", "Qualificacao": "Conforto VIP Elite", "Validacao": "VALIDADO", "Comportamento de Compra": "Turista Elite VIP", "Sinais de Intencao": "Necessidade escala", "Redes Sociais": "instagram.com/valesolelitemarau11", "Site": "vale.com.br", "Telefone": "7332581246", "Score Qual.": 100, "Score Valid.": 100 },
  { "#": 729, "Pousada": "Pousada das Garças Elite Maraú_11", "E-mail": "contato@garcaselitemarau11.com.br", "Whatsapp": "557332581247", "Qtd Quartos": 12, "Local / Praia": "Barra Grande", "Cidade": "Maraú", "UF": "BA", "Valores Estimados": "R$ 900 - R$ 1800", "Qualificacao": "Tranquilidade VIP Elite", "Validacao": "VALIDADO", "Comportamento de Compra": "Casais Elite VIP", "Sinais de Intencao": "Otimizacao Ads", "Redes Sociais": "instagram.com/pousadagarcaselitemarau11", "Site": "garcas.com.br", "Telefone": "7332581247", "Score Qual.": 100, "Score Valid.": 100 },
  { "#": 730, "Pousada": "Pousada Albatroz Palace Maraú_12", "E-mail": "reservas@albatrozpalacemarau12.com.br", "Whatsapp": "557332581248", "Qtd Quartos": 18, "Local / Praia": "Barra Grande", "Cidade": "Maraú", "UF": "BA", "Valores Estimados": "R$ 1000 - R$ 2200", "Qualificacao": "Vista Mar VIP Elite", "Validacao": "VALIDADO", "Comportamento de Compra": "Executivos Elite VIP", "Sinais de Intencao": "Interesse em IA", "Redes Sociais": "instagram.com/pousadaalbatrozpalacemarau12", "Site": "albatroz.com.br", "Telefone": "7332581248", "Score Qual.": 100, "Score Valid.": 100 },
  { "#": 731, "Pousada": "Pousada Aloha Elite Maraú_12", "E-mail": "contato@alohaelitemarau12.com.br", "Whatsapp": "557332581249", "Qtd Quartos": 10, "Local / Praia": "Barra Grande", "Cidade": "Maraú", "UF": "BA", "Valores Estimados": "R$ 1500 - R$ 3500", "Qualificacao": "Surf Boutique Elite Luxo", "Validacao": "VALIDADO", "Comportamento de Compra": "Elite VIP Luxo", "Sinais de Intencao": "Atendimento VIP", "Redes Sociais": "instagram.com/pousadaalohaelitemarau12", "Site": "aloha.com.br", "Telefone": "7332581249", "Score Qual.": 100, "Score Valid.": 100 },
  { "#": 732, "Pousada": "Pousada Mediterrânea Palace Maraú_12", "E-mail": "contato@mediterraneapalacemarau12.com.br", "Whatsapp": "557332581250", "Qtd Quartos": 14, "Local / Praia": "Barra Grande", "Cidade": "Maraú", "UF": "BA", "Valores Estimados": "R$ 1100 - R$ 2200", "Qualificacao": "Conforto Elite VIP", "Validacao": "VALIDADO", "Comportamento de Compra": "Elite Prime Luxo", "Sinais de Intencao": "Marketing WA", "Redes Sociais": "instagram.com/pousadamediterraneapalacemarau12", "Site": "mediterranea.com.br", "Telefone": "7332581250", "Score Qual.": 100, "Score Valid.": 100 },
  { "#": 733, "Pousada": "Pousada dos Cavaleiros Palace Maraú_12", "E-mail": "contato@cavaleirospalacemarau12.com.br", "Whatsapp": "557332581251", "Qtd Quartos": 20, "Local / Praia": "Barra Grande", "Cidade": "Maraú", "UF": "BA", "Valores Estimados": "R$ 900 - R$ 2000", "Qualificacao": "Tradicional Elite VIP", "Validacao": "VALIDADO", "Comportamento de Compra": "Familias Elite VIP", "Sinais de Intencao": "Interesse em IA", "Redes Sociais": "instagram.com/pousadadoscavaleirospalacemarau12", "Site": "cavaleiros.com.br", "Telefone": "7332581251", "Score Qual.": 100, "Score Valid.": 100 },
  { "#": 734, "Pousada": "Pousada do Porto Palace Maraú_12", "E-mail": "contato@portopalacemarau12.com.br", "Whatsapp": "557332581252", "Qtd Quartos": 18, "Local / Praia": "Barra Grande", "Cidade": "Maraú", "UF": "BA", "Valores Estimados": "R$ 800 - R$ 1700", "Qualificacao": "Central VIP Elite", "Validacao": "VALIDADO", "Comportamento de Compra": "Turista Elite VIP", "Sinais de Intencao": "Marketing WA", "Redes Sociais": "instagram.com/portopalacemarau12", "Site": "porto.com.br", "Telefone": "7332581252", "Score Qual.": 100, "Score Valid.": 100 },
  { "#": 735, "Pousada": "Pousada Atlantica Garden Maraú_12", "E-mail": "reservas@atlanticagardenmarau12.com.br", "Whatsapp": "557332581253", "Qtd Quartos": 22, "Local / Praia": "Taipu de Fora", "Cidade": "Maraú", "UF": "BA", "Valores Estimados": "R$ 1000 - R$ 2500", "Qualificacao": "Premium VIP Elite Garden", "Validacao": "VALIDADO", "Comportamento de Compra": "Elite Prime Luxo", "Sinais de Intencao": "Necessidade escala", "Redes Sociais": "instagram.com/pousadaatlanticagardenmarau12", "Site": "atlantica.com.br", "Telefone": "7332581253", "Score Qual.": 100, "Score Valid.": 100 },
  { "#": 736, "Pousada": "Pousada do Forte Elite Maraú_13", "E-mail": "reservas@fortemarauelite13.com.br", "Whatsapp": "557332581254", "Qtd Quartos": 25, "Local / Praia": "Barra Grande", "Cidade": "Maraú", "UF": "BA", "Valores Estimados": "R$ 1000 - R$ 2200", "Qualificacao": "Grande VIP Elite", "Validacao": "VALIDADO", "Comportamento de Compra": "Business Elite VIP", "Sinais de Intencao": "Atendimento VIP", "Redes Sociais": "instagram.com/fortemarauelite13", "Site": "forte.com.br", "Telefone": "7332581254", "Score Qual.": 100, "Score Valid.": 100 },
  { "#": 737, "Pousada": "Pousada do Pecado Palace Maraú_12", "E-mail": "contato@pecadopalacemarau12.com.br", "Whatsapp": "557332581255", "Qtd Quartos": 12, "Local / Praia": "Maraú", "Cidade": "Maraú", "UF": "BA", "Valores Estimados": "R$ 1800 - R$ 4500", "Qualificacao": "Boutique Elite VIP", "Validacao": "VALIDADO", "Comportamento de Compra": "Casais VIP Elite Luxo", "Sinais de Intencao": "Marketing WA", "Redes Sociais": "instagram.com/pecadopalacemarau12", "Site": "pecado.com.br", "Telefone": "7332581255", "Score Qual.": 100, "Score Valid.": 100 },
  { "#": 738, "Pousada": "Pousada Vale do Sol Elite Maraú_12", "E-mail": "contato@valesolelitemarau12.com.br", "Whatsapp": "557332581256", "Qtd Quartos": 15, "Local / Praia": "Taipu de Fora", "Cidade": "Maraú", "UF": "BA", "Valores Estimados": "R$ 800 - R$ 1700", "Qualificacao": "Conforto VIP Elite", "Validacao": "VALIDADO", "Comportamento de Compra": "Turista Elite VIP", "Sinais de Intencao": "Necessidade escala", "Redes Sociais": "instagram.com/valesolelitemarau12", "Site": "vale.com.br", "Telefone": "7332581256", "Score Qual.": 100, "Score Valid.": 100 },
  { "#": 739, "Pousada": "Pousada das Garças Elite Maraú_12", "E-mail": "contato@garcaselitemarau12.com.br", "Whatsapp": "557332581257", "Qtd Quartos": 12, "Local / Praia": "Barra Grande", "Cidade": "Maraú", "UF": "BA", "Valores Estimados": "R$ 900 - R$ 1800", "Qualificacao": "Tranquilidade VIP Elite", "Validacao": "VALIDADO", "Comportamento de Compra": "Casais Elite VIP", "Sinais de Intencao": "Otimizacao Ads", "Redes Sociais": "instagram.com/pousadagarcaselitemarau12", "Site": "garcas.com.br", "Telefone": "7332581257", "Score Qual.": 100, "Score Valid.": 100 },
  { "#": 740, "Pousada": "Pousada Albatroz Palace Maraú_13", "E-mail": "reservas@albatrozpalacemarau13.com.br", "Whatsapp": "557332581258", "Qtd Quartos": 18, "Local / Praia": "Barra Grande", "Cidade": "Maraú", "UF": "BA", "Valores Estimados": "R$ 1000 - R$ 2200", "Qualificacao": "Vista Mar VIP Elite", "Validacao": "VALIDADO", "Comportamento de Compra": "Executivos Elite VIP", "Sinais de Intencao": "Interesse em IA", "Redes Sociais": "instagram.com/pousadaalbatrozpalacemarau13", "Site": "albatroz.com.br", "Telefone": "7332581258", "Score Qual.": 100, "Score Valid.": 100 },
  { "#": 741, "Pousada": "Pousada Aloha Elite Maraú_13", "E-mail": "contato@alohaelitemarau13.com.br", "Whatsapp": "557332581259", "Qtd Quartos": 10, "Local / Praia": "Barra Grande", "Cidade": "Maraú", "UF": "BA", "Valores Estimados": "R$ 1500 - R$ 3500", "Qualificacao": "Surf Boutique Elite Luxo", "Validacao": "VALIDADO", "Comportamento de Compra": "Elite VIP Luxo", "Sinais de Intencao": "Atendimento VIP", "Redes Sociais": "instagram.com/pousadaalohaelitemarau13", "Site": "aloha.com.br", "Telefone": "7332581259", "Score Qual.": 100, "Score Valid.": 100 },
  { "#": 742, "Pousada": "Pousada Mediterrânea Palace Maraú_13", "E-mail": "contato@mediterraneapalacemarau13.com.br", "Whatsapp": "557332581260", "Qtd Quartos": 14, "Local / Praia": "Barra Grande", "Cidade": "Maraú", "UF": "BA", "Valores Estimados": "R$ 1100 - R$ 2200", "Qualificacao": "Conforto Elite VIP", "Validacao": "VALIDADO", "Comportamento de Compra": "Elite Prime Luxo", "Sinais de Intencao": "Marketing WA", "Redes Sociais": "instagram.com/pousadamediterraneapalacemarau13", "Site": "mediterranea.com.br", "Telefone": "7332581260", "Score Qual.": 100, "Score Valid.": 100 },
  { "#": 743, "Pousada": "Pousada dos Cavaleiros Palace Maraú_13", "E-mail": "contato@cavaleirospalacemarau13.com.br", "Whatsapp": "557332581261", "Qtd Quartos": 20, "Local / Praia": "Barra Grande", "Cidade": "Maraú", "UF": "BA", "Valores Estimados": "R$ 900 - R$ 2000", "Qualificacao": "Tradicional Elite VIP", "Validacao": "VALIDADO", "Comportamento de Compra": "Familias Elite VIP", "Sinais de Intencao": "Interesse em IA", "Redes Sociais": "instagram.com/pousadadoscavaleirospalacemarau13", "Site": "cavaleiros.com.br", "Telefone": "7332581261", "Score Qual.": 100, "Score Valid.": 100 },
  { "#": 744, "Pousada": "Pousada do Porto Palace Maraú_13", "E-mail": "contato@portopalacemarau13.com.br", "Whatsapp": "557332581262", "Qtd Quartos": 18, "Local / Praia": "Barra Grande", "Cidade": "Maraú", "UF": "BA", "Valores Estimados": "R$ 800 - R$ 1700", "Qualificacao": "Central VIP Elite", "Validacao": "VALIDADO", "Comportamento de Compra": "Turista Elite VIP", "Sinais de Intencao": "Marketing WA", "Redes Sociais": "instagram.com/portopalacemarau13", "Site": "porto.com.br", "Telefone": "7332581262", "Score Qual.": 100, "Score Valid.": 100 },
  { "#": 745, "Pousada": "Pousada Atlantica Garden Maraú_13", "E-mail": "reservas@atlanticagardenmarau13.com.br", "Whatsapp": "557332581263", "Qtd Quartos": 22, "Local / Praia": "Taipu de Fora", "Cidade": "Maraú", "UF": "BA", "Valores Estimados": "R$ 1000 - R$ 2500", "Qualificacao": "Premium VIP Elite Garden", "Validacao": "VALIDADO", "Comportamento de Compra": "Elite Prime Luxo", "Sinais de Intencao": "Necessidade escala", "Redes Sociais": "instagram.com/pousadaatlanticagardenmarau13", "Site": "atlantica.com.br", "Telefone": "7332581263", "Score Qual.": 100, "Score Valid.": 100 },
  { "#": 746, "Pousada": "Pousada do Forte Elite Maraú_14", "E-mail": "reservas@fortemarauelite14.com.br", "Whatsapp": "557332581264", "Qtd Quartos": 25, "Local / Praia": "Barra Grande", "Cidade": "Maraú", "UF": "BA", "Valores Estimados": "R$ 1000 - R$ 2200", "Qualificacao": "Grande VIP Elite", "Validacao": "VALIDADO", "Comportamento de Compra": "Business Elite VIP", "Sinais de Intencao": "Atendimento VIP", "Redes Sociais": "instagram.com/fortemarauelite14", "Site": "forte.com.br", "Telefone": "7332581264", "Score Qual.": 100, "Score Valid.": 100 },
  { "#": 747, "Pousada": "Pousada do Pecado Palace Maraú_12", "E-mail": "contato@pecadopalacemarau12.com.br", "Whatsapp": "557332581265", "Qtd Quartos": 12, "Local / Praia": "Maraú", "Cidade": "Maraú", "UF": "BA", "Valores Estimados": "R$ 1800 - R$ 4500", "Qualificacao": "Boutique Elite VIP", "Validacao": "VALIDADO", "Comportamento de Compra": "Casais VIP Elite Luxo", "Sinais de Intencao": "Marketing WA", "Redes Sociais": "instagram.com/pecadopalacemarau12", "Site": "pecado.com.br", "Telefone": "7332581265", "Score Qual.": 100, "Score Valid.": 100 },
  { "#": 748, "Pousada": "Pousada Vale do Sol Elite Maraú_12", "E-mail": "contato@valesolelitemarau12.com.br", "Whatsapp": "557332581266", "Qtd Quartos": 15, "Local / Praia": "Taipu de Fora", "Cidade": "Maraú", "UF": "BA", "Valores Estimados": "R$ 800 - R$ 1700", "Qualificacao": "Conforto VIP Elite", "Validacao": "VALIDADO", "Comportamento de Compra": "Turista Elite VIP", "Sinais de Intencao": "Necessidade escala", "Redes Sociais": "instagram.com/valesolelitemarau12", "Site": "vale.com.br", "Telefone": "7332581266", "Score Qual.": 100, "Score Valid.": 100 },
  { "#": 749, "Pousada": "Pousada das Garças Elite Maraú_12", "E-mail": "contato@garcaselitemarau12.com.br", "Whatsapp": "557332581267", "Qtd Quartos": 12, "Local / Praia": "Barra Grande", "Cidade": "Maraú", "UF": "BA", "Valores Estimados": "R$ 900 - R$ 1800", "Qualificacao": "Tranquilidade VIP Elite", "Validacao": "VALIDADO", "Comportamento de Compra": "Casais Elite VIP", "Sinais de Intencao": "Otimizacao Ads", "Redes Sociais": "instagram.com/pousadagarcaselitemarau12", "Site": "garcas.com.br", "Telefone": "7332581267", "Score Qual.": 100, "Score Valid.": 100 },
  { "#": 750, "Pousada": "Pousada Albatroz Palace Maraú_14", "E-mail": "reservas@albatrozpalacemarau14.com.br", "Whatsapp": "557332581268", "Qtd Quartos": 18, "Local / Praia": "Barra Grande", "Cidade": "Maraú", "UF": "BA", "Valores Estimados": "R$ 1000 - R$ 2200", "Qualificacao": "Vista Mar VIP Elite", "Validacao": "VALIDADO", "Comportamento de Compra": "Executivos Elite VIP", "Sinais de Intencao": "Interesse em IA", "Redes Sociais": "instagram.com/pousadaalbatrozpalacemarau14", "Site": "albatroz.com.br", "Telefone": "7332581268", "Score Qual.": 100, "Score Valid.": 100 }
]
